<Data><Panels><Panel><Struct name="Out_In"><Component id="0" name="Out"><Layout name="Out_Center_Single" Number="0" Position="[[0.5, 0.5, 1, 1]]" Uniformity="0"><Entity bbox="[0.5, 0.5, 1, 1]" real_bbox="[0.5575, 0.4425, 0.7701, 0.7701]" mask="[4609,1,4611,1,4613,1,4765,1,4767,1,4769,1,4771,2,4774,146,4921,2,4924,1,4926,1,4933,1,5078,1,5080,1,5082,1,5084,1,5092,1,5235,1,5237,1,5239,1,5252,1,5254,136,5391,1,5393,1,5395,1,5412,1,5548,1,5550,1,5552,20,5573,129,5703,1,5705,1,5707,1,5709,1,5731,1,5733,126,5860,1,5862,1,5864,1,5866,25,5892,1,6016,1,6018,1,6020,1,6022,28,6051,1,6171,1,6173,1,6175,1,6177,34,6212,117,6330,1,6332,1,6334,36,6371,112,6484,2,6487,1,6489,41,6531,110,6642,1,6644,1,6646,1,6690,1,6692,107,6800,1,6802,1,6849,1,6851,102,6954,1,6956,1,6958,1,7009,1,7011,100,7112,1,7114,1,7169,1,7267,1,7269,1,7271,1,7273,56,7330,93,7424,1,7426,1,7488,1,7490,89,7580,1,7582,1,7584,1,7648,1,7736,1,7738,1,7740,2,7743,65,7809,83,7893,1,7895,1,7897,71,7969,79,8049,1,8051,1,8054,1,8127,1,8204,1,8206,1,8208,1,8210,77,8288,1,8360,1,8362,1,8364,1,8366,1,8446,1,8448,68,8517,1,8519,1,8521,1,8607,1,8674,1,8676,1,8678,88,8767,62,8830,1,8833,1,8835,1,8926,1,8986,1,8988,1,8990,1,9085,1,9087,54,9142,1,9144,1,9146,1,9148,98,9247,52,9300,1,9302,1,9405,1,9453,1,9455,1,9457,1,9459,106,9566,1,9611,1,9613,1,9615,1,9617,107,9725,1,9770,1,9772,1,9885,1,9930,1,9932,112,10045,1,10091,1,10204,1,10252,1,10364,1,10413,1,10523,1,10525,49,10575,108,10684,51,10736,107,10844,52,10897,105,11003,54,11058,104,11163,1,11218,1,11322,1,11324,55,11380,102,11483,57,11541,101,11643,58,11702,99,11802,60,11863,98,11962,61,12024,96,12121,1,12184,1,12280,1,12345,1,12440,1,12506,1,12600,1,12602,65,12668,91,12760,1,12828,1,12920,1,12989,1,13079,1,13150,1,13239,1,13311,1,13398,1,13472,1,13558,1,13633,1,13718,1,13794,1,13878,1,13955,1,14037,1,14116,1,14197,1,14199,78,14278,78,14357,1,14438,1,14517,1,14599,1,14676,1,14760,1,14836,1,14921,1,14996,1,15082,1,15156,1,15243,1,15315,1,15404,1,15475,1,15565,1,15634,1,15726,1,15794,1,15796,91,15888,65,15954,1,16048,1,16114,1,16209,1,16274,1,16370,1,16433,1,16435,96,16532,61,16594,98,16693,60,16754,99,16854,58,16913,1,17014,1,17072,1,17175,1,17231,1,17233,103,17337,55,17393,104,17498,54,17553,105,17659,52,17712,107,17820,51,17872,108,17981,49,18031,1,18141,1,18190,1,18192,110,18303,47,18351,112,18464,45,18510,1,18624,1,18669,1,18671,114,18786,44,18831,115,18947,42,18990,117,19108,41,19150,118,19269,39,19309,120,19430,38,19469,1,19590,1,19628,1,19751,1,19788,1,19912,1,19947,1,19949,124,20074,33,20108,1,20234,1,20266,1,20268,127,20396,31,20428,128,20557,29,20587,130,20718,28,20747,131,20879,27,20907,132,21040,25,21066,1,21200,1,21225,1,21227,134,21362,23,21386,136,21523,21,21545,1,21683,1,21704,1,21706,138,21845,19,21865,140,22006,18,22025,141,22167,17,22185,142,22328,15,22344,1,22488,1,22503,1,22505,144,22650,13,22664,146,22811,12,22824,147,22972,10,22983,149,23133,9,23143,150,23294,7,23302,1,23454,1,23462,1,23615,1,23621,1,23776,1,23781,1,23783,154,23938,2,23941,1,24098,1,24100,1,24102,157,24260,1]" Type="1" Size="5" Color="0" Angle="2" /></Layout></Component><Component id="1" name="In"><Layout name="In_Distribute_Four" Number="0" Position="[[0.42, 0.42, 0.15, 0.15], [0.42, 0.58, 0.15, 0.15], [0.58, 0.42, 0.15, 0.15], [0.58, 0.58, 0.15, 0.15]]" Uniformity="0"><Entity bbox="[0.42, 0.58, 0.15, 0.15]" real_bbox="[0.4312, 0.575, 0.0812, 0.0937]" mask="[10167,13,10326,15,10486,15,10647,13,10807,13,10968,11,11129,9,11289,9,11450,7,11610,7,11771,5,11932,3,12092,3]" Type="1" Size="2" Color="3" Angle="7" /></Layout></Component><Component id="2" name="Mesh"><Layout name="Mesh_Layout" Number="2" Position="[[0.08, 0.08, 0.5, 0.08], [0.5, 0.08, 0.92, 0.08], [0.5, 0.08, 0.5, 0.5], [0.92, 0.08, 0.92, 0.5], [0.92, 0.5, 0.92, 0.92], [0.5, 0.5, 0.92, 0.5], [0.5, 0.92, 0.92, 0.92], [0.08, 0.92, 0.5, 0.92], [0.5, 0.5, 0.5, 0.92], [0.08, 0.5, 0.08, 0.92], [0.08, 0.08, 0.08, 0.5], [0.08, 0.5, 0.5, 0.5]]" Uniformity="1"><Entity bbox="[0.5, 0.08, 0.5, 0.5]" real_bbox="[0.6503, -0.0753, 0.3193, 0.3193]" mask="[12653,69,12812,71,12973,69]" Type="6" Size="0" Color="0" Angle="0" /><Entity bbox="[0.08, 0.5, 0.5, 0.5]" real_bbox="[-0.0753, 0.3497, 0.3193, 0.3193]" mask="[1841,1,2000,3,2160,3,2320,3,2480,3,2640,3,2800,3,2960,3,3120,3,3280,3,3440,3,3600,3,3760,3,3920,3,4080,3,4240,3,4400,3,4560,3,4720,3,4880,3,5040,3,5200,3,5360,3,5520,3,5680,3,5840,3,6000,3,6160,3,6320,3,6480,3,6640,3,6800,3,6960,3,7120,3,7280,3,7440,3,7600,3,7760,3,7920,3,8080,3,8240,3,8400,3,8560,3,8720,3,8880,3,9040,3,9200,3,9360,3,9520,3,9680,3,9840,3,10000,3,10160,3,10320,3,10480,3,10640,3,10800,3,10960,3,11120,3,11280,3,11440,3,11600,3,11760,3,11920,3,12080,3,12240,3,12400,3,12560,3,12720,3,12880,3,13041,1]" Type="6" Size="0" Color="0" Angle="0" /><Entity bbox="[0.08, 0.08, 0.5, 0.08]" real_bbox="[-0.0753, -0.0753, 0.3193, 0.3193]" mask="[1773,1,1932,3,2092,3,2252,3,2412,3,2572,3,2732,3,2892,3,3052,3,3212,3,3372,3,3532,3,3692,3,3852,3,4012,3,4172,3,4332,3,4492,3,4652,3,4812,3,4972,3,5132,3,5292,3,5452,3,5612,3,5772,3,5932,3,6092,3,6252,3,6412,3,6572,3,6732,3,6892,3,7052,3,7212,3,7372,3,7532,3,7692,3,7852,3,8012,3,8172,3,8332,3,8492,3,8652,3,8812,3,8972,3,9132,3,9292,3,9452,3,9612,3,9772,3,9932,3,10092,3,10252,3,10412,3,10572,3,10732,3,10892,3,11052,3,11212,3,11372,3,11532,3,11692,3,11852,3,12012,3,12172,3,12332,3,12492,3,12652,3,12812,3,12973,1]" Type="6" Size="0" Color="0" Angle="0" /></Layout></Component></Struct></Panel><Panel><Struct name="Out_In"><Component id="0" name="Out"><Layout name="Out_Center_Single" Number="0" Position="[[0.5, 0.5, 1, 1]]" Uniformity="0"><Entity bbox="[0.5, 0.5, 1, 1]" real_bbox="[0.5, 0.5, 0.8142, 0.8142]" mask="[2480,1,2482,1,2639,1,2641,1,2643,1,2798,1,2804,1,2957,1,2965,1,3116,1,3126,1,3275,1,3287,1,3434,1,3448,1,3593,1,3609,1,3752,1,3770,1,3911,1,3931,1,4070,1,4092,1,4229,1,4253,1,4388,1,4414,1,4547,1,4575,1,4706,1,4736,1,4865,1,4897,1,5024,1,5058,1,5183,1,5219,1,5342,1,5380,1,5501,1,5541,1,5660,1,5702,1,5819,1,5863,1,5978,1,6024,1,6137,1,6185,1,6296,1,6346,1,6455,1,6507,1,6614,1,6668,1,6773,1,6829,1,6932,1,6990,1,7091,1,7151,1,7250,1,7312,1,7409,1,7473,1,7568,1,7634,1,7727,1,7795,1,7886,1,7956,1,8045,1,8117,1,8204,1,8278,1,8363,1,8439,1,8522,1,8600,1,8681,1,8761,1,8840,1,8922,1,8999,1,9083,1,9158,1,9244,1,9317,1,9405,1,9476,1,9566,1,9635,1,9727,1,9794,1,9888,1,9953,1,10049,1,10112,1,10210,1,10271,1,10371,1,10430,1,10532,1,10589,1,10693,1,10748,1,10854,1,10907,1,11015,1,11066,1,11176,1,11225,1,11337,1,11384,1,11498,1,11543,1,11659,1,11702,1,11820,1,11861,1,11981,1,12020,1,12142,1,12179,1,12303,1,12338,1,12464,1,12497,1,12625,1,12656,1,12786,1,12816,1,12818,127,12946,1,12976,1,13106,1,13137,1,13265,1,13298,1,13424,1,13459,1,13583,1,13620,1,13742,1,13781,1,13901,1,13942,1,14060,1,14103,1,14219,1,14264,1,14378,1,14425,1,14537,1,14586,1,14696,1,14747,1,14855,1,14908,1,15014,1,15069,1,15173,1,15230,1,15332,1,15391,1,15491,1,15552,1,15650,1,15713,1,15809,1,15874,1,15968,1,16035,1,16127,1,16196,1,16286,1,16357,1,16445,1,16518,1,16604,1,16679,1,16763,1,16840,1,16922,1,17001,1,17081,1,17162,1,17240,1,17323,1,17399,1,17484,1,17558,1,17645,1,17717,1,17806,1,17876,1,17967,1,18035,1,18128,1,18194,1,18289,1,18353,1,18450,1,18512,1,18611,1,18671,1,18772,1,18830,1,18933,1,18989,1,19094,1,19148,1,19255,1,19307,1,19416,1,19466,1,19577,1,19625,1,19738,1,19784,1,19899,1,19943,1,20060,1,20102,1,20221,1,20261,1,20382,1,20420,1,20543,1,20579,1,20704,1,20738,1,20865,1,20897,1,21026,1,21056,1,21187,1,21215,1,21348,1,21374,1,21509,1,21533,1,21670,1,21692,1,21831,1,21851,1,21992,1,22010,1,22153,1,22169,1,22314,1,22328,1,22475,1,22487,1,22636,1,22646,1,22797,1,22805,1,22958,1,22964,1,23119,1,23121,1,23123,1,23280,1,23282,1]" Type="2" Size="4" Color="0" Angle="2" /></Layout></Component><Component id="1" name="In"><Layout name="In_Distribute_Four" Number="0" Position="[[0.42, 0.42, 0.15, 0.15], [0.42, 0.58, 0.15, 0.15], [0.58, 0.42, 0.15, 0.15], [0.58, 0.58, 0.15, 0.15]]" Uniformity="0"><Entity bbox="[0.58, 0.58, 0.15, 0.15]" real_bbox="[0.5875, 0.575, 0.0812, 0.0937]" mask="[14167,13,14326,15,14486,15,14647,13,14807,13,14968,11,15129,9,15289,9,15450,7,15610,7,15771,5,15932,3,16092,3]" Type="1" Size="2" Color="4" Angle="7" /></Layout></Component><Component id="2" name="Mesh"><Layout name="Mesh_Layout" Number="2" Position="[[0.08, 0.08, 0.5, 0.08], [0.5, 0.08, 0.92, 0.08], [0.5, 0.08, 0.5, 0.5], [0.92, 0.08, 0.92, 0.5], [0.92, 0.5, 0.92, 0.92], [0.5, 0.5, 0.92, 0.5], [0.5, 0.92, 0.92, 0.92], [0.08, 0.92, 0.5, 0.92], [0.5, 0.5, 0.5, 0.92], [0.08, 0.5, 0.08, 0.92], [0.08, 0.08, 0.08, 0.5], [0.08, 0.5, 0.5, 0.5]]" Uniformity="1"><Entity bbox="[0.92, 0.08, 0.92, 0.5]" real_bbox="[1.069, -0.0753, 0.3193, 0.3193]" mask="[23373,69,23532,71,23693,69]" Type="6" Size="0" Color="0" Angle="0" /><Entity bbox="[0.5, 0.08, 0.5, 0.5]" real_bbox="[0.6503, -0.0753, 0.3193, 0.3193]" mask="[12653,69,12812,71,12973,69]" Type="6" Size="0" Color="0" Angle="0" /><Entity bbox="[0.08, 0.5, 0.5, 0.5]" real_bbox="[-0.0753, 0.3497, 0.3193, 0.3193]" mask="[1841,1,2000,3,2160,3,2320,3,2480,3,2640,3,2800,3,2960,3,3120,3,3280,3,3440,3,3600,3,3760,3,3920,3,4080,3,4240,3,4400,3,4560,3,4720,3,4880,3,5040,3,5200,3,5360,3,5520,3,5680,3,5840,3,6000,3,6160,3,6320,3,6480,3,6640,3,6800,3,6960,3,7120,3,7280,3,7440,3,7600,3,7760,3,7920,3,8080,3,8240,3,8400,3,8560,3,8720,3,8880,3,9040,3,9200,3,9360,3,9520,3,9680,3,9840,3,10000,3,10160,3,10320,3,10480,3,10640,3,10800,3,10960,3,11120,3,11280,3,11440,3,11600,3,11760,3,11920,3,12080,3,12240,3,12400,3,12560,3,12720,3,12880,3,13041,1]" Type="6" Size="0" Color="0" Angle="0" /></Layout></Component></Struct></Panel><Panel><Struct name="Out_In"><Component id="0" name="Out"><Layout name="Out_Center_Single" Number="0" Position="[[0.5, 0.5, 1, 1]]" Uniformity="0"><Entity bbox="[0.5, 0.5, 1, 1]" real_bbox="[0.5155, 0.4845, 0.6684, 0.6684]" mask="[4537,1,4695,1,4697,1,4700,2,4854,1,4858,1,4860,1,4862,1,4864,1,4866,1,4869,1,5014,1,5022,1,5026,1,5028,1,5030,1,5032,2,5035,1,5173,1,5175,17,5193,1,5195,1,5197,1,5199,1,5201,1,5332,1,5334,23,5358,1,5361,1,5363,1,5365,1,5367,2,5370,122,5493,1,5525,1,5527,1,5529,1,5531,1,5533,1,5535,117,5653,37,5691,1,5693,1,5695,1,5698,1,5700,1,5702,1,5811,1,5858,1,5860,1,5863,1,5865,1,5867,1,5971,1,6025,1,6027,1,6029,1,6031,1,6033,4,6038,92,6131,59,6191,2,6194,1,6196,1,6198,1,6200,1,6202,87,6290,68,6359,1,6361,1,6363,86,6450,1,6522,1,6524,84,6609,1,6682,1,6768,1,6842,1,6844,84,6929,73,7003,1,7087,1,7163,1,7165,82,7248,75,7324,82,7407,1,7483,1,7565,1,7567,76,7644,81,7726,1,7803,1,7885,1,7964,1,8044,1,8046,78,8125,79,8205,78,8284,1,8363,1,8444,1,8523,1,8525,79,8605,77,8683,1,8764,1,8766,75,8842,1,8924,1,8926,76,9003,81,9085,76,9162,83,9246,74,9321,84,9406,74,9481,1,9565,1,9567,72,9640,1,9725,1,9727,71,9799,1,9885,1,9959,1,10046,1,10118,1,10205,1,10207,70,10278,1,10366,1,10437,1,10526,1,10596,1,10686,1,10756,1,10847,1,10916,1,11006,1,11075,1,11166,1,11168,67,11236,91,11328,66,11395,91,11487,1,11553,1,11647,1,11649,64,11714,1,11807,1,11872,1,11874,93,11968,63,12032,1,12127,1,12129,63,12193,94,12288,63,12352,96,12449,61,12511,97,12609,61,12671,1,12768,1,12829,1,12831,97,12929,1,12989,1,13089,1,13149,1,13249,1,13308,1,13408,1,13410,58,13469,99,13569,1,13627,1,13729,1,13786,1,13889,1,13891,55,13947,1,14050,1,14105,1,14107,102,14210,55,14266,1,14369,1,14425,1,14530,1,14586,1,14690,1,14747,1,14850,1,14852,56,14909,101,15011,58,15070,100,15171,59,15231,99,15331,1,15391,1,15491,1,15552,1,15651,1,15713,1,15811,1,15874,1,15970,1,15972,63,16036,95,16132,1,16196,1,16291,1,16293,64,16358,94,16453,65,16519,92,16612,1,16679,1,16772,1,16774,66,16841,91,16933,68,17002,90,17093,69,17163,86,17250,1,17252,71,17324,83,17408,1,17410,74,17485,81,17567,1,17569,76,17646,78,17725,1,17806,1,17881,1,17883,1,17967,1,18040,1,18042,1,18128,1,18198,1,18200,1,18289,1,18355,1,18357,1,18450,1,18513,1,18515,1,18611,1,18671,1,18673,1,18675,97,18773,55,18829,1,18831,1,18933,1,18987,1,18989,1,19094,1,19145,1,19147,1,19255,1,19302,1,19304,1,19306,1,19416,1,19461,1,19463,1,19577,1,19619,1,19621,1,19738,1,19777,1,19779,1,19781,118,19900,36,19937,1,20060,1,20093,1,20095,1,20221,1,20251,1,20253,129,20383,25,20409,1,20411,132,20544,23,20568,1,20570,134,20705,20,20726,1,20728,137,20866,16,20883,1,20885,1,20887,139,21027,14,21042,1,21044,143,21188,11,21200,1,21202,146,21349,8,21358,1,21509,1,21514,1,21516,1,21670,1,21672,1,21674,1,21676,155,21832,1,21834]" Type="3" Size="3" Color="0" Angle="2" /></Layout></Component><Component id="1" name="In"><Layout name="In_Distribute_Four" Number="0" Position="[[0.42, 0.42, 0.15, 0.15], [0.42, 0.58, 0.15, 0.15], [0.58, 0.42, 0.15, 0.15], [0.58, 0.58, 0.15, 0.15]]" Uniformity="0"><Entity bbox="[0.42, 0.42, 0.15, 0.15]" real_bbox="[0.4344, 0.4188, 0.1125, 0.1187]" mask="[9820,17,9979,19,10140,17,10300,17,10461,15,10621,15,10782,13,10942,13,11103,11,11263,11,11424,9,11584,9,11745,7,11906,5,12066,5,12227,3,12387,3,12548,1]" Type="1" Size="5" Color="5" Angle="7" /></Layout></Component><Component id="2" name="Mesh"><Layout name="Mesh_Layout" Number="2" Position="[[0.08, 0.08, 0.5, 0.08], [0.5, 0.08, 0.92, 0.08], [0.5, 0.08, 0.5, 0.5], [0.92, 0.08, 0.92, 0.5], [0.92, 0.5, 0.92, 0.92], [0.5, 0.5, 0.92, 0.5], [0.5, 0.92, 0.92, 0.92], [0.08, 0.92, 0.5, 0.92], [0.5, 0.5, 0.5, 0.92], [0.08, 0.5, 0.08, 0.92], [0.08, 0.08, 0.08, 0.5], [0.08, 0.5, 0.5, 0.5]]" Uniformity="1"><Entity bbox="[0.92, 0.5, 0.92, 0.92]" real_bbox="[1.0668, 0.3519, 0.3149, 0.3149]" mask="[23441,68,23600,70,23761,68]" Type="6" Size="0" Color="0" Angle="0" /><Entity bbox="[0.08, 0.5, 0.5, 0.5]" real_bbox="[-0.0753, 0.3497, 0.3193, 0.3193]" mask="[1841,1,2000,3,2160,3,2320,3,2480,3,2640,3,2800,3,2960,3,3120,3,3280,3,3440,3,3600,3,3760,3,3920,3,4080,3,4240,3,4400,3,4560,3,4720,3,4880,3,5040,3,5200,3,5360,3,5520,3,5680,3,5840,3,6000,3,6160,3,6320,3,6480,3,6640,3,6800,3,6960,3,7120,3,7280,3,7440,3,7600,3,7760,3,7920,3,8080,3,8240,3,8400,3,8560,3,8720,3,8880,3,9040,3,9200,3,9360,3,9520,3,9680,3,9840,3,10000,3,10160,3,10320,3,10480,3,10640,3,10800,3,10960,3,11120,3,11280,3,11440,3,11600,3,11760,3,11920,3,12080,3,12240,3,12400,3,12560,3,12720,3,12880,3,13041,1]" Type="6" Size="0" Color="0" Angle="0" /><Entity bbox="[0.08, 0.92, 0.5, 0.92]" real_bbox="[-0.0753, 0.7685, 0.3193, 0.3193]" mask="[1908,1,2067,3,2227,3,2387,3,2547,3,2707,3,2867,3,3027,3,3187,3,3347,3,3507,3,3667,3,3827,3,3987,3,4147,3,4307,3,4467,3,4627,3,4787,3,4947,3,5107,3,5267,3,5427,3,5587,3,5747,3,5907,3,6067,3,6227,3,6387,3,6547,3,6707,3,6867,3,7027,3,7187,3,7347,3,7507,3,7667,3,7827,3,7987,3,8147,3,8307,3,8467,3,8627,3,8787,3,8947,3,9107,3,9267,3,9427,3,9587,3,9747,3,9907,3,10067,3,10227,3,10387,3,10547,3,10707,3,10867,3,11027,3,11187,3,11347,3,11507,3,11667,3,11827,3,11987,3,12147,3,12307,3,12467,3,12627,3,12787,3,12947,3,13108,1]" Type="6" Size="0" Color="0" Angle="0" /></Layout></Component></Struct></Panel><Panel><Struct name="Out_In"><Component id="0" name="Out"><Layout name="Out_Center_Single" Number="0" Position="[[0.5, 0.5, 1, 1]]" Uniformity="0"><Entity bbox="[0.5, 0.5, 1, 1]" real_bbox="[0.5, 0.5, 0.6438, 0.6438]" mask="[4671,101,4830,103,4990,103,5150,103,5310,103,5470,103,5630,103,5790,103,5950,103,6110,103,6270,103,6430,103,6590,103,6750,103,6910,103,7070,103,7230,103,7390,103,7550,103,7710,103,7870,103,8030,103,8190,103,8350,103,8510,103,8670,103,8830,103,8990,103,9150,103,9310,103,9470,103,9630,103,9790,103,9950,103,10110,103,10270,103,10430,103,10590,103,10750,103,10910,103,11070,103,11230,103,11390,103,11550,103,11710,103,11870,103,12030,103,12190,103,12350,103,12510,103,12670,103,12830,103,12990,103,13150,103,13310,103,13470,103,13630,103,13790,103,13950,103,14110,103,14270,103,14430,103,14590,103,14750,103,14910,103,15070,103,15230,103,15390,103,15550,103,15710,103,15870,103,16030,103,16190,103,16350,103,16510,103,16670,103,16830,103,16990,103,17150,103,17310,103,17470,103,17630,103,17790,103,17950,103,18110,103,18270,103,18430,103,18590,103,18750,103,18910,103,19070,103,19230,103,19390,103,19550,103,19710,103,19870,103,20030,103,20190,103,20350,103,20510,103,20670,103,20830,103,20991,101]" Type="2" Size="5" Color="0" Angle="5" /></Layout></Component><Component id="1" name="In"><Layout name="In_Distribute_Four" Number="0" Position="[[0.42, 0.42, 0.15, 0.15], [0.42, 0.58, 0.15, 0.15], [0.58, 0.42, 0.15, 0.15], [0.58, 0.58, 0.15, 0.15]]" Uniformity="0"><Entity bbox="[0.42, 0.42, 0.15, 0.15]" real_bbox="[0.4232, 0.4232, 0.0895, 0.0895]" mask="[9663,1,9822,1,9824,1,9826,1,9828,1,9830,151,9982,6,9989,1,9991,1,9993,149,10143,7,10151,2,10154,1,10156,146,10303,12,10316,1,10462,1,10475,1,10622,1,10635,1,10637,146,10784,10,10795,1,10942,1,10944,9,10954,1,11103,1,11105,7,11113,1,11263,1,11271,1,11273,150,11424,6,11431,1,11584,1,11589,1,11591,153,11745,3,11749,1,11904,1,11906,1,11908,1,12065,1,12067,1]" Type="1" Size="2" Color="7" Angle="4" /></Layout></Component><Component id="2" name="Mesh"><Layout name="Mesh_Layout" Number="2" Position="[[0.08, 0.08, 0.5, 0.08], [0.5, 0.08, 0.92, 0.08], [0.5, 0.08, 0.5, 0.5], [0.92, 0.08, 0.92, 0.5], [0.92, 0.5, 0.92, 0.92], [0.5, 0.5, 0.92, 0.5], [0.5, 0.92, 0.92, 0.92], [0.08, 0.92, 0.5, 0.92], [0.5, 0.5, 0.5, 0.92], [0.08, 0.5, 0.08, 0.92], [0.08, 0.08, 0.08, 0.5], [0.08, 0.5, 0.5, 0.5]]" Uniformity="1"><Entity bbox="[0.92, 0.5, 0.92, 0.92]" real_bbox="[1.0668, 0.3519, 0.3149, 0.3149]" mask="[23441,68,23600,70,23761,68]" Type="6" Size="0" Color="0" Angle="0" /><Entity bbox="[0.08, 0.5, 0.5, 0.5]" real_bbox="[-0.0753, 0.3497, 0.3193, 0.3193]" mask="[1841,1,2000,3,2160,3,2320,3,2480,3,2640,3,2800,3,2960,3,3120,3,3280,3,3440,3,3600,3,3760,3,3920,3,4080,3,4240,3,4400,3,4560,3,4720,3,4880,3,5040,3,5200,3,5360,3,5520,3,5680,3,5840,3,6000,3,6160,3,6320,3,6480,3,6640,3,6800,3,6960,3,7120,3,7280,3,7440,3,7600,3,7760,3,7920,3,8080,3,8240,3,8400,3,8560,3,8720,3,8880,3,9040,3,9200,3,9360,3,9520,3,9680,3,9840,3,10000,3,10160,3,10320,3,10480,3,10640,3,10800,3,10960,3,11120,3,11280,3,11440,3,11600,3,11760,3,11920,3,12080,3,12240,3,12400,3,12560,3,12720,3,12880,3,13041,1]" Type="6" Size="0" Color="0" Angle="0" /><Entity bbox="[0.08, 0.92, 0.5, 0.92]" real_bbox="[-0.0753, 0.7685, 0.3193, 0.3193]" mask="[1908,1,2067,3,2227,3,2387,3,2547,3,2707,3,2867,3,3027,3,3187,3,3347,3,3507,3,3667,3,3827,3,3987,3,4147,3,4307,3,4467,3,4627,3,4787,3,4947,3,5107,3,5267,3,5427,3,5587,3,5747,3,5907,3,6067,3,6227,3,6387,3,6547,3,6707,3,6867,3,7027,3,7187,3,7347,3,7507,3,7667,3,7827,3,7987,3,8147,3,8307,3,8467,3,8627,3,8787,3,8947,3,9107,3,9267,3,9427,3,9587,3,9747,3,9907,3,10067,3,10227,3,10387,3,10547,3,10707,3,10867,3,11027,3,11187,3,11347,3,11507,3,11667,3,11827,3,11987,3,12147,3,12307,3,12467,3,12627,3,12787,3,12947,3,13108,1]" Type="6" Size="0" Color="0" Angle="0" /></Layout></Component></Struct></Panel><Panel><Struct name="Out_In"><Component id="0" name="Out"><Layout name="Out_Center_Single" Number="0" Position="[[0.5, 0.5, 1, 1]]" Uniformity="0"><Entity bbox="[0.5, 0.5, 1, 1]" real_bbox="[0.5, 0.4594, 0.7688, 0.7375]" mask="[3101,3,3260,7,3420,10,3579,14,3738,18,3897,22,4057,25,4216,29,4375,33,4534,37,4694,40,4853,44,5012,48,5171,52,5331,55,5490,60,5649,64,5808,68,5968,71,6127,75,6286,79,6445,83,6605,86,6764,89,6923,91,7082,92,7242,92,7401,93,7560,94,7719,95,7879,95,8038,96,8197,97,8356,98,8516,98,8675,99,8834,100,8993,101,9153,101,9312,102,9471,103,9630,104,9790,104,9949,105,10108,106,10267,107,10427,107,10586,108,10745,109,10904,110,11064,110,11223,111,11382,112,11541,113,11701,113,11860,114,12019,115,12178,116,12338,116,12497,117,12656,118,12816,118,12976,118,13137,117,13298,116,13458,116,13619,115,13780,114,13941,113,14101,113,14262,112,14423,111,14584,110,14744,110,14905,109,15066,108,15227,107,15387,107,15548,106,15709,105,15870,104,16030,104,16191,103,16352,102,16513,101,16673,101,16834,100,16995,99,17156,98,17316,98,17477,97,17638,96,17799,95,17959,95,18120,94,18281,93,18442,92,18602,92,18763,91,18924,89,19085,86,19245,83,19406,79,19567,75,19728,71,19888,68,20049,64,20210,60,20371,55,20531,52,20692,48,20853,44,21014,40,21174,37,21335,33,21496,29,21657,25,21817,22,21978,18,22139,14,22300,10,22460,7,22621,3]" Type="3" Size="4" Color="0" Angle="5" /></Layout></Component><Component id="1" name="In"><Layout name="In_Distribute_Four" Number="0" Position="[[0.42, 0.42, 0.15, 0.15], [0.42, 0.58, 0.15, 0.15], [0.58, 0.42, 0.15, 0.15], [0.58, 0.58, 0.15, 0.15]]" Uniformity="0"><Entity bbox="[0.42, 0.58, 0.15, 0.15]" real_bbox="[0.4232, 0.5794, 0.0895, 0.0895]" mask="[9688,1,9847,1,9849,1,9851,1,9853,1,9855,151,10007,6,10014,1,10016,1,10018,149,10168,7,10176,2,10179,1,10181,146,10328,12,10341,1,10487,1,10500,1,10647,1,10660,1,10662,146,10809,10,10820,1,10967,1,10969,9,10979,1,11128,1,11130,7,11138,1,11288,1,11296,1,11298,150,11449,6,11456,1,11609,1,11614,1,11616,153,11770,3,11774,1,11929,1,11931,1,11933,1,12090,1,12092,1]" Type="1" Size="2" Color="8" Angle="4" /></Layout></Component><Component id="2" name="Mesh"><Layout name="Mesh_Layout" Number="2" Position="[[0.08, 0.08, 0.5, 0.08], [0.5, 0.08, 0.92, 0.08], [0.5, 0.08, 0.5, 0.5], [0.92, 0.08, 0.92, 0.5], [0.92, 0.5, 0.92, 0.92], [0.5, 0.5, 0.92, 0.5], [0.5, 0.92, 0.92, 0.92], [0.08, 0.92, 0.5, 0.92], [0.5, 0.5, 0.5, 0.92], [0.08, 0.5, 0.08, 0.92], [0.08, 0.08, 0.08, 0.5], [0.08, 0.5, 0.5, 0.5]]" Uniformity="1"><Entity bbox="[0.5, 0.08, 0.5, 0.5]" real_bbox="[0.6503, -0.0753, 0.3193, 0.3193]" mask="[12653,69,12812,71,12973,69]" Type="6" Size="0" Color="0" Angle="0" /><Entity bbox="[0.08, 0.5, 0.5, 0.5]" real_bbox="[-0.0753, 0.3497, 0.3193, 0.3193]" mask="[1841,1,2000,3,2160,3,2320,3,2480,3,2640,3,2800,3,2960,3,3120,3,3280,3,3440,3,3600,3,3760,3,3920,3,4080,3,4240,3,4400,3,4560,3,4720,3,4880,3,5040,3,5200,3,5360,3,5520,3,5680,3,5840,3,6000,3,6160,3,6320,3,6480,3,6640,3,6800,3,6960,3,7120,3,7280,3,7440,3,7600,3,7760,3,7920,3,8080,3,8240,3,8400,3,8560,3,8720,3,8880,3,9040,3,9200,3,9360,3,9520,3,9680,3,9840,3,10000,3,10160,3,10320,3,10480,3,10640,3,10800,3,10960,3,11120,3,11280,3,11440,3,11600,3,11760,3,11920,3,12080,3,12240,3,12400,3,12560,3,12720,3,12880,3,13041,1]" Type="6" Size="0" Color="0" Angle="0" /><Entity bbox="[0.08, 0.08, 0.5, 0.08]" real_bbox="[-0.0753, -0.0753, 0.3193, 0.3193]" mask="[1773,1,1932,3,2092,3,2252,3,2412,3,2572,3,2732,3,2892,3,3052,3,3212,3,3372,3,3532,3,3692,3,3852,3,4012,3,4172,3,4332,3,4492,3,4652,3,4812,3,4972,3,5132,3,5292,3,5452,3,5612,3,5772,3,5932,3,6092,3,6252,3,6412,3,6572,3,6732,3,6892,3,7052,3,7212,3,7372,3,7532,3,7692,3,7852,3,8012,3,8172,3,8332,3,8492,3,8652,3,8812,3,8972,3,9132,3,9292,3,9452,3,9612,3,9772,3,9932,3,10092,3,10252,3,10412,3,10572,3,10732,3,10892,3,11052,3,11212,3,11372,3,11532,3,11692,3,11852,3,12012,3,12172,3,12332,3,12492,3,12652,3,12812,3,12973,1]" Type="6" Size="0" Color="0" Angle="0" /></Layout></Component></Struct></Panel><Panel><Struct name="Out_In"><Component id="0" name="Out"><Layout name="Out_Center_Single" Number="0" Position="[[0.5, 0.5, 1, 1]]" Uniformity="0"><Entity bbox="[0.5, 0.5, 1, 1]" real_bbox="[0.5, 0.5, 0.6188, 0.7188]" mask="[5012,59,5172,59,5331,61,5490,63,5650,63,5809,65,5969,65,6128,67,6287,69,6447,69,6606,71,6766,71,6925,73,7085,73,7244,75,7403,77,7563,77,7722,79,7882,79,8041,81,8200,83,8360,83,8519,85,8679,85,8838,87,8998,87,9157,89,9316,91,9476,91,9635,93,9795,93,9954,95,10113,97,10273,97,10432,99,10592,99,10751,101,10911,101,11070,103,11229,105,11389,105,11548,107,11708,107,11867,109,12026,111,12186,111,12345,113,12505,113,12664,115,12824,115,12984,115,13145,113,13305,113,13466,111,13626,111,13787,109,13948,107,14108,107,14269,105,14429,105,14590,103,14751,101,14911,101,15072,99,15232,99,15393,97,15553,97,15714,95,15875,93,16035,93,16196,91,16356,91,16517,89,16678,87,16838,87,16999,85,17159,85,17320,83,17480,83,17641,81,17802,79,17962,79,18123,77,18283,77,18444,75,18605,73,18765,73,18926,71,19086,71,19247,69,19407,69,19568,67,19729,65,19889,65,20050,63,20210,63,20371,61,20532,59,20692,59]" Type="4" Size="3" Color="0" Angle="5" /></Layout></Component><Component id="1" name="In"><Layout name="In_Distribute_Four" Number="0" Position="[[0.42, 0.42, 0.15, 0.15], [0.42, 0.58, 0.15, 0.15], [0.58, 0.42, 0.15, 0.15], [0.58, 0.58, 0.15, 0.15]]" Uniformity="0"><Entity bbox="[0.58, 0.58, 0.15, 0.15]" real_bbox="[0.5816, 0.5816, 0.1204, 0.1204]" mask="[13525,1,13527,1,13529,1,13685,1,13688,1,13690,1,13692,1,13694,151,13846,4,13851,2,13854,1,13856,150,14007,9,14017,1,14019,1,14165,1,14167,11,14179,1,14181,1,14183,1,14326,1,14328,12,14341,1,14343,1,14345,141,14487,16,14504,142,14647,16,14664,142,14807,1,14822,1,14967,1,14981,1,15127,1,15140,1,15288,1,15299,1,15448,1,15458,1,15609,1,15617,1,15768,1,15770,6,15777,152,15930,1,15935,1,16089,1,16094,1,16250,1,16253,1,16409,1,16411,1,16413,157,16571]" Type="1" Size="5" Color="9" Angle="4" /></Layout></Component><Component id="2" name="Mesh"><Layout name="Mesh_Layout" Number="2" Position="[[0.08, 0.08, 0.5, 0.08], [0.5, 0.08, 0.92, 0.08], [0.5, 0.08, 0.5, 0.5], [0.92, 0.08, 0.92, 0.5], [0.92, 0.5, 0.92, 0.92], [0.5, 0.5, 0.92, 0.5], [0.5, 0.92, 0.92, 0.92], [0.08, 0.92, 0.5, 0.92], [0.5, 0.5, 0.5, 0.92], [0.08, 0.5, 0.08, 0.92], [0.08, 0.08, 0.08, 0.5], [0.08, 0.5, 0.5, 0.5]]" Uniformity="1"><Entity bbox="[0.92, 0.08, 0.92, 0.5]" real_bbox="[1.069, -0.0753, 0.3193, 0.3193]" mask="[23373,69,23532,71,23693,69]" Type="6" Size="0" Color="0" Angle="0" /><Entity bbox="[0.5, 0.08, 0.5, 0.5]" real_bbox="[0.6503, -0.0753, 0.3193, 0.3193]" mask="[12653,69,12812,71,12973,69]" Type="6" Size="0" Color="0" Angle="0" /><Entity bbox="[0.08, 0.5, 0.5, 0.5]" real_bbox="[-0.0753, 0.3497, 0.3193, 0.3193]" mask="[1841,1,2000,3,2160,3,2320,3,2480,3,2640,3,2800,3,2960,3,3120,3,3280,3,3440,3,3600,3,3760,3,3920,3,4080,3,4240,3,4400,3,4560,3,4720,3,4880,3,5040,3,5200,3,5360,3,5520,3,5680,3,5840,3,6000,3,6160,3,6320,3,6480,3,6640,3,6800,3,6960,3,7120,3,7280,3,7440,3,7600,3,7760,3,7920,3,8080,3,8240,3,8400,3,8560,3,8720,3,8880,3,9040,3,9200,3,9360,3,9520,3,9680,3,9840,3,10000,3,10160,3,10320,3,10480,3,10640,3,10800,3,10960,3,11120,3,11280,3,11440,3,11600,3,11760,3,11920,3,12080,3,12240,3,12400,3,12560,3,12720,3,12880,3,13041,1]" Type="6" Size="0" Color="0" Angle="0" /></Layout></Component></Struct></Panel><Panel><Struct name="Out_In"><Component id="0" name="Out"><Layout name="Out_Center_Single" Number="0" Position="[[0.5, 0.5, 1, 1]]" Uniformity="0"><Entity bbox="[0.5, 0.5, 1, 1]" real_bbox="[0.5, 0.3875, 0.7938, 0.6938]" mask="[2837,1,2995,4,3153,6,3312,7,3470,9,3628,11,3786,13,3945,14,4103,16,4261,18,4419,20,4578,21,4736,23,4894,25,5052,27,5211,28,5369,30,5527,32,5686,33,5844,35,6002,37,6160,39,6319,40,6477,42,6635,44,6793,46,6952,47,7110,49,7268,51,7426,53,7585,54,7743,56,7901,58,8059,60,8218,61,8376,63,8534,65,8692,67,8851,68,9009,70,9167,72,9325,74,9484,75,9642,77,9800,79,9958,81,10117,82,10275,84,10433,86,10592,87,10750,89,10908,91,11066,93,11225,94,11383,96,11541,98,11699,100,11858,101,12016,103,12174,105,12332,107,12491,108,12649,110,12808,111,12969,110,13131,108,13292,107,13454,105,13616,103,13778,101,13939,100,14101,98,14263,96,14425,94,14586,93,14748,91,14910,89,15072,87,15233,86,15395,84,15557,82,15718,81,15880,79,16042,77,16204,75,16365,74,16527,72,16689,70,16851,68,17012,67,17174,65,17336,63,17498,61,17659,60,17821,58,17983,56,18145,54,18306,53,18468,51,18630,49,18792,47,18953,46,19115,44,19277,42,19439,40,19600,39,19762,37,19924,35,20086,33,20247,32,20409,30,20571,28,20732,27,20894,25,21056,23,21218,21,21379,20,21541,18,21703,16,21865,14,22026,13,22188,11,22350,9,22512,7,22673,6,22835,4,22997,1]" Type="1" Size="5" Color="0" Angle="5" /></Layout></Component><Component id="1" name="In"><Layout name="In_Distribute_Four" Number="0" Position="[[0.42, 0.42, 0.15, 0.15], [0.42, 0.58, 0.15, 0.15], [0.58, 0.42, 0.15, 0.15], [0.58, 0.58, 0.15, 0.15]]" Uniformity="0"><Entity bbox="[0.58, 0.58, 0.15, 0.15]" real_bbox="[0.5625, 0.575, 0.0812, 0.0938]" mask="[13532,3,13692,3,13851,5,14010,7,14170,7,14329,9,14489,9,14648,11,14807,13,14967,13,15126,15,15286,15,15447,13]" Type="1" Size="2" Color="4" Angle="3" /></Layout></Component><Component id="2" name="Mesh"><Layout name="Mesh_Layout" Number="2" Position="[[0.08, 0.08, 0.5, 0.08], [0.5, 0.08, 0.92, 0.08], [0.5, 0.08, 0.5, 0.5], [0.92, 0.08, 0.92, 0.5], [0.92, 0.5, 0.92, 0.92], [0.5, 0.5, 0.92, 0.5], [0.5, 0.92, 0.92, 0.92], [0.08, 0.92, 0.5, 0.92], [0.5, 0.5, 0.5, 0.92], [0.08, 0.5, 0.08, 0.92], [0.08, 0.08, 0.08, 0.5], [0.08, 0.5, 0.5, 0.5]]" Uniformity="1"><Entity bbox="[0.92, 0.08, 0.92, 0.5]" real_bbox="[1.069, -0.0753, 0.3193, 0.3193]" mask="[23373,69,23532,71,23693,69]" Type="6" Size="0" Color="0" Angle="0" /><Entity bbox="[0.5, 0.08, 0.5, 0.5]" real_bbox="[0.6503, -0.0753, 0.3193, 0.3193]" mask="[12653,69,12812,71,12973,69]" Type="6" Size="0" Color="0" Angle="0" /><Entity bbox="[0.08, 0.5, 0.5, 0.5]" real_bbox="[-0.0753, 0.3497, 0.3193, 0.3193]" mask="[1841,1,2000,3,2160,3,2320,3,2480,3,2640,3,2800,3,2960,3,3120,3,3280,3,3440,3,3600,3,3760,3,3920,3,4080,3,4240,3,4400,3,4560,3,4720,3,4880,3,5040,3,5200,3,5360,3,5520,3,5680,3,5840,3,6000,3,6160,3,6320,3,6480,3,6640,3,6800,3,6960,3,7120,3,7280,3,7440,3,7600,3,7760,3,7920,3,8080,3,8240,3,8400,3,8560,3,8720,3,8880,3,9040,3,9200,3,9360,3,9520,3,9680,3,9840,3,10000,3,10160,3,10320,3,10480,3,10640,3,10800,3,10960,3,11120,3,11280,3,11440,3,11600,3,11760,3,11920,3,12080,3,12240,3,12400,3,12560,3,12720,3,12880,3,13041,1]" Type="6" Size="0" Color="0" Angle="0" /></Layout></Component></Struct></Panel><Panel><Struct name="Out_In"><Component id="0" name="Out"><Layout name="Out_Center_Single" Number="0" Position="[[0.5, 0.5, 1, 1]]" Uniformity="0"><Entity bbox="[0.5, 0.5, 1, 1]" real_bbox="[0.5, 0.5, 0.5812, 0.5813]" mask="[5476,91,5635,93,5795,93,5955,93,6115,93,6275,93,6435,93,6595,93,6755,93,6915,93,7075,93,7235,93,7395,93,7555,93,7715,93,7875,93,8035,93,8195,93,8355,93,8515,93,8675,93,8835,93,8995,93,9155,93,9315,93,9475,93,9635,93,9795,93,9955,93,10115,93,10275,93,10435,93,10595,93,10755,93,10915,93,11075,93,11235,93,11395,93,11555,93,11715,93,11875,93,12035,93,12195,93,12355,93,12515,93,12675,93,12835,93,12995,93,13155,93,13315,93,13475,93,13635,93,13795,93,13955,93,14115,93,14275,93,14435,93,14595,93,14755,93,14915,93,15075,93,15235,93,15395,93,15555,93,15715,93,15875,93,16035,93,16195,93,16355,93,16515,93,16675,93,16835,93,16995,93,17155,93,17315,93,17475,93,17635,93,17795,93,17955,93,18115,93,18275,93,18435,93,18595,93,18755,93,18915,93,19075,93,19235,93,19395,93,19555,93,19715,93,19875,93,20035,93,20196,91]" Type="2" Size="4" Color="0" Angle="5" /></Layout></Component><Component id="1" name="In"><Layout name="In_Distribute_Four" Number="0" Position="[[0.42, 0.42, 0.15, 0.15], [0.42, 0.58, 0.15, 0.15], [0.58, 0.42, 0.15, 0.15], [0.58, 0.58, 0.15, 0.15]]" Uniformity="0"><Entity bbox="[0.42, 0.42, 0.15, 0.15]" real_bbox="[0.4062, 0.4188, 0.0812, 0.0938]" mask="[9507,3,9667,3,9826,5,9985,7,10145,7,10304,9,10464,9,10623,11,10782,13,10942,13,11101,15,11261,15,11422,13]" Type="1" Size="2" Color="5" Angle="3" /></Layout></Component><Component id="2" name="Mesh"><Layout name="Mesh_Layout" Number="2" Position="[[0.08, 0.08, 0.5, 0.08], [0.5, 0.08, 0.92, 0.08], [0.5, 0.08, 0.5, 0.5], [0.92, 0.08, 0.92, 0.5], [0.92, 0.5, 0.92, 0.92], [0.5, 0.5, 0.92, 0.5], [0.5, 0.92, 0.92, 0.92], [0.08, 0.92, 0.5, 0.92], [0.5, 0.5, 0.5, 0.92], [0.08, 0.5, 0.08, 0.92], [0.08, 0.08, 0.08, 0.5], [0.08, 0.5, 0.5, 0.5]]" Uniformity="1"><Entity bbox="[0.92, 0.5, 0.92, 0.92]" real_bbox="[1.0668, 0.3519, 0.3149, 0.3149]" mask="[23441,68,23600,70,23761,68]" Type="6" Size="0" Color="0" Angle="0" /><Entity bbox="[0.08, 0.5, 0.5, 0.5]" real_bbox="[-0.0753, 0.3497, 0.3193, 0.3193]" mask="[1841,1,2000,3,2160,3,2320,3,2480,3,2640,3,2800,3,2960,3,3120,3,3280,3,3440,3,3600,3,3760,3,3920,3,4080,3,4240,3,4400,3,4560,3,4720,3,4880,3,5040,3,5200,3,5360,3,5520,3,5680,3,5840,3,6000,3,6160,3,6320,3,6480,3,6640,3,6800,3,6960,3,7120,3,7280,3,7440,3,7600,3,7760,3,7920,3,8080,3,8240,3,8400,3,8560,3,8720,3,8880,3,9040,3,9200,3,9360,3,9520,3,9680,3,9840,3,10000,3,10160,3,10320,3,10480,3,10640,3,10800,3,10960,3,11120,3,11280,3,11440,3,11600,3,11760,3,11920,3,12080,3,12240,3,12400,3,12560,3,12720,3,12880,3,13041,1]" Type="6" Size="0" Color="0" Angle="0" /><Entity bbox="[0.08, 0.92, 0.5, 0.92]" real_bbox="[-0.0753, 0.7685, 0.3193, 0.3193]" mask="[1908,1,2067,3,2227,3,2387,3,2547,3,2707,3,2867,3,3027,3,3187,3,3347,3,3507,3,3667,3,3827,3,3987,3,4147,3,4307,3,4467,3,4627,3,4787,3,4947,3,5107,3,5267,3,5427,3,5587,3,5747,3,5907,3,6067,3,6227,3,6387,3,6547,3,6707,3,6867,3,7027,3,7187,3,7347,3,7507,3,7667,3,7827,3,7987,3,8147,3,8307,3,8467,3,8627,3,8787,3,8947,3,9107,3,9267,3,9427,3,9587,3,9747,3,9907,3,10067,3,10227,3,10387,3,10547,3,10707,3,10867,3,11027,3,11187,3,11347,3,11507,3,11667,3,11827,3,11987,3,12147,3,12307,3,12467,3,12627,3,12787,3,12947,3,13108,1]" Type="6" Size="0" Color="0" Angle="0" /></Layout></Component></Struct></Panel><Panel><Struct name="Out_In"><Component id="0" name="Out"><Layout name="Out_Center_Single" Number="0" Position="[[0.5, 0.5, 1, 1]]" Uniformity="0"><Entity bbox="[0.5, 0.5, 1, 1]" real_bbox="[0.5, 0.4656, 0.6813, 0.65]" mask="[4223,3,4382,7,4542,10,4701,14,4860,18,5020,21,5179,25,5338,28,5497,32,5657,35,5816,39,5975,43,6134,47,6294,50,6453,54,6612,58,6771,62,6931,65,7090,69,7249,73,7408,77,7568,79,7727,81,7886,82,8046,82,8205,83,8364,84,8523,85,8683,85,8842,86,9001,87,9160,88,9320,88,9479,89,9638,90,9797,91,9957,91,10116,92,10275,93,10434,94,10594,94,10753,95,10912,96,11072,96,11231,97,11390,98,11549,99,11709,99,11868,100,12027,101,12186,102,12346,102,12505,103,12664,104,12824,104,12984,104,13145,103,13306,102,13466,102,13627,101,13788,100,13949,99,14109,99,14270,98,14431,97,14592,96,14752,96,14913,95,15074,94,15234,94,15395,93,15556,92,15717,91,15877,91,16038,90,16199,89,16360,88,16520,88,16681,87,16842,86,17003,85,17163,85,17324,84,17485,83,17646,82,17806,82,17967,81,18128,79,18288,77,18449,73,18610,69,18771,65,18931,62,19092,58,19253,54,19414,50,19574,47,19735,43,19896,39,20057,35,20217,32,20378,28,20539,25,20700,21,20860,18,21021,14,21182,10,21342,7,21503,3]" Type="3" Size="3" Color="0" Angle="5" /></Layout></Component><Component id="1" name="In"><Layout name="In_Distribute_Four" Number="2" Position="[[0.42, 0.42, 0.15, 0.15], [0.42, 0.58, 0.15, 0.15], [0.58, 0.42, 0.15, 0.15], [0.58, 0.58, 0.15, 0.15]]" Uniformity="0"><Entity bbox="[0.58, 0.42, 0.15, 0.15]" real_bbox="[0.575, 0.4188, 0.1063, 0.1063]" mask="[13501,15,13660,17,13820,17,13980,17,14140,17,14300,17,14460,17,14620,17,14780,17,14940,17,15100,17,15260,17,15420,17,15580,17,15740,17,15900,17,16061,15]" Type="2" Size="5" Color="6" Angle="3" /><Entity bbox="[0.42, 0.58, 0.15, 0.15]" real_bbox="[0.4188, 0.575, 0.1063, 0.1063]" mask="[9526,15,9685,17,9845,17,10005,17,10165,17,10325,17,10485,17,10645,17,10805,17,10965,17,11125,17,11285,17,11445,17,11605,17,11765,17,11925,17,12086,15]" Type="2" Size="5" Color="6" Angle="3" /><Entity bbox="[0.58, 0.58, 0.15, 0.15]" real_bbox="[0.575, 0.575, 0.1063, 0.1063]" mask="[13526,15,13685,17,13845,17,14005,17,14165,17,14325,17,14485,17,14645,17,14805,17,14965,17,15125,17,15285,17,15445,17,15605,17,15765,17,15925,17,16086,15]" Type="2" Size="5" Color="6" Angle="3" /></Layout></Component><Component id="2" name="Mesh"><Layout name="Mesh_Layout" Number="2" Position="[[0.08, 0.08, 0.5, 0.08], [0.5, 0.08, 0.92, 0.08], [0.5, 0.08, 0.5, 0.5], [0.92, 0.08, 0.92, 0.5], [0.92, 0.5, 0.92, 0.92], [0.5, 0.5, 0.92, 0.5], [0.5, 0.92, 0.92, 0.92], [0.08, 0.92, 0.5, 0.92], [0.5, 0.5, 0.5, 0.92], [0.08, 0.5, 0.08, 0.92], [0.08, 0.08, 0.08, 0.5], [0.08, 0.5, 0.5, 0.5]]" Uniformity="1"><Entity bbox="[0.5, 0.08, 0.92, 0.08]" real_bbox="[0.3519, -0.0731, 0.3149, 0.3149]" mask="[12653,1,12812,3,12972,3,13132,3,13292,3,13452,3,13612,3,13772,3,13932,3,14092,3,14252,3,14412,3,14572,3,14732,3,14892,3,15052,3,15212,3,15372,3,15532,3,15692,3,15852,3,16012,3,16172,3,16332,3,16492,3,16652,3,16812,3,16972,3,17132,3,17292,3,17452,3,17612,3,17772,3,17932,3,18092,3,18252,3,18412,3,18572,3,18732,3,18892,3,19052,3,19212,3,19372,3,19532,3,19692,3,19852,3,20012,3,20172,3,20332,3,20492,3,20652,3,20812,3,20972,3,21132,3,21292,3,21452,3,21612,3,21772,3,21932,3,22092,3,22252,3,22412,3,22572,3,22732,3,22892,3,23052,3,23212,3,23372,3,23532,3,23693,1]" Type="6" Size="0" Color="0" Angle="0" /><Entity bbox="[0.92, 0.08, 0.92, 0.5]" real_bbox="[1.069, -0.0753, 0.3193, 0.3193]" mask="[23373,69,23532,71,23693,69]" Type="6" Size="0" Color="0" Angle="0" /><Entity bbox="[0.92, 0.5, 0.92, 0.92]" real_bbox="[1.0668, 0.3519, 0.3149, 0.3149]" mask="[23441,68,23600,70,23761,68]" Type="6" Size="0" Color="0" Angle="0" /></Layout></Component></Struct></Panel><Panel><Struct name="Out_In"><Component id="0" name="Out"><Layout name="Out_Center_Single" Number="0" Position="[[0.5, 0.5, 1, 1]]" Uniformity="0"><Entity bbox="[0.5, 0.5, 1, 1]" real_bbox="[0.5, 0.4656, 0.6813, 0.65]" mask="[4223,3,4382,7,4542,10,4701,14,4860,18,5020,21,5179,25,5338,28,5497,32,5657,35,5816,39,5975,43,6134,47,6294,50,6453,54,6612,58,6771,62,6931,65,7090,69,7249,73,7408,77,7568,79,7727,81,7886,82,8046,82,8205,83,8364,84,8523,85,8683,85,8842,86,9001,87,9160,88,9320,88,9479,89,9638,90,9797,91,9957,91,10116,92,10275,93,10434,94,10594,94,10753,95,10912,96,11072,96,11231,97,11390,98,11549,99,11709,99,11868,100,12027,101,12186,102,12346,102,12505,103,12664,104,12824,104,12984,104,13145,103,13306,102,13466,102,13627,101,13788,100,13949,99,14109,99,14270,98,14431,97,14592,96,14752,96,14913,95,15074,94,15234,94,15395,93,15556,92,15717,91,15877,91,16038,90,16199,89,16360,88,16520,88,16681,87,16842,86,17003,85,17163,85,17324,84,17485,83,17646,82,17806,82,17967,81,18128,79,18288,77,18449,73,18610,69,18771,65,18931,62,19092,58,19253,54,19414,50,19574,47,19735,43,19896,39,20057,35,20217,32,20378,28,20539,25,20700,21,20860,18,21021,14,21182,10,21342,7,21503,3]" Type="3" Size="3" Color="0" Angle="5" /></Layout></Component><Component id="1" name="In"><Layout name="In_Distribute_Four" Number="2" Position="[[0.42, 0.42, 0.15, 0.15], [0.42, 0.58, 0.15, 0.15], [0.58, 0.42, 0.15, 0.15], [0.58, 0.58, 0.15, 0.15]]" Uniformity="0"><Entity bbox="[0.58, 0.42, 0.15, 0.15]" real_bbox="[0.575, 0.4188, 0.1063, 0.1063]" mask="[13501,15,13660,17,13820,17,13980,17,14140,17,14300,17,14460,17,14620,17,14780,17,14940,17,15100,17,15260,17,15420,17,15580,17,15740,17,15900,17,16061,15]" Type="2" Size="5" Color="6" Angle="3" /><Entity bbox="[0.42, 0.58, 0.15, 0.15]" real_bbox="[0.4188, 0.575, 0.1063, 0.1063]" mask="[9526,15,9685,17,9845,17,10005,17,10165,17,10325,17,10485,17,10645,17,10805,17,10965,17,11125,17,11285,17,11445,17,11605,17,11765,17,11925,17,12086,15]" Type="2" Size="5" Color="6" Angle="3" /><Entity bbox="[0.58, 0.58, 0.15, 0.15]" real_bbox="[0.575, 0.575, 0.1063, 0.1063]" mask="[13526,15,13685,17,13845,17,14005,17,14165,17,14325,17,14485,17,14645,17,14805,17,14965,17,15125,17,15285,17,15445,17,15605,17,15765,17,15925,17,16086,15]" Type="2" Size="5" Color="6" Angle="3" /></Layout></Component><Component id="2" name="Mesh"><Layout name="Mesh_Layout" Number="2" Position="[[0.08, 0.08, 0.5, 0.08], [0.5, 0.08, 0.92, 0.08], [0.5, 0.08, 0.5, 0.5], [0.92, 0.08, 0.92, 0.5], [0.92, 0.5, 0.92, 0.92], [0.5, 0.5, 0.92, 0.5], [0.5, 0.92, 0.92, 0.92], [0.08, 0.92, 0.5, 0.92], [0.5, 0.5, 0.5, 0.92], [0.08, 0.5, 0.08, 0.92], [0.08, 0.08, 0.08, 0.5], [0.08, 0.5, 0.5, 0.5]]" Uniformity="1"><Entity bbox="[0.5, 0.08, 0.5, 0.5]" real_bbox="[0.6503, -0.0753, 0.3193, 0.3193]" mask="[12653,69,12812,71,12973,69]" Type="6" Size="0" Color="0" Angle="0" /><Entity bbox="[0.08, 0.5, 0.5, 0.5]" real_bbox="[-0.0753, 0.3497, 0.3193, 0.3193]" mask="[1841,1,2000,3,2160,3,2320,3,2480,3,2640,3,2800,3,2960,3,3120,3,3280,3,3440,3,3600,3,3760,3,3920,3,4080,3,4240,3,4400,3,4560,3,4720,3,4880,3,5040,3,5200,3,5360,3,5520,3,5680,3,5840,3,6000,3,6160,3,6320,3,6480,3,6640,3,6800,3,6960,3,7120,3,7280,3,7440,3,7600,3,7760,3,7920,3,8080,3,8240,3,8400,3,8560,3,8720,3,8880,3,9040,3,9200,3,9360,3,9520,3,9680,3,9840,3,10000,3,10160,3,10320,3,10480,3,10640,3,10800,3,10960,3,11120,3,11280,3,11440,3,11600,3,11760,3,11920,3,12080,3,12240,3,12400,3,12560,3,12720,3,12880,3,13041,1]" Type="6" Size="0" Color="0" Angle="0" /><Entity bbox="[0.08, 0.08, 0.5, 0.08]" real_bbox="[-0.0753, -0.0753, 0.3193, 0.3193]" mask="[1773,1,1932,3,2092,3,2252,3,2412,3,2572,3,2732,3,2892,3,3052,3,3212,3,3372,3,3532,3,3692,3,3852,3,4012,3,4172,3,4332,3,4492,3,4652,3,4812,3,4972,3,5132,3,5292,3,5452,3,5612,3,5772,3,5932,3,6092,3,6252,3,6412,3,6572,3,6732,3,6892,3,7052,3,7212,3,7372,3,7532,3,7692,3,7852,3,8012,3,8172,3,8332,3,8492,3,8652,3,8812,3,8972,3,9132,3,9292,3,9452,3,9612,3,9772,3,9932,3,10092,3,10252,3,10412,3,10572,3,10732,3,10892,3,11052,3,11212,3,11372,3,11532,3,11692,3,11852,3,12012,3,12172,3,12332,3,12492,3,12652,3,12812,3,12973,1]" Type="6" Size="0" Color="0" Angle="0" /></Layout></Component></Struct></Panel><Panel><Struct name="Out_In"><Component id="0" name="Out"><Layout name="Out_Center_Single" Number="0" Position="[[0.5, 0.5, 1, 1]]" Uniformity="0"><Entity bbox="[0.5, 0.5, 1, 1]" real_bbox="[0.5, 0.4656, 0.6813, 0.65]" mask="[4223,3,4382,7,4542,10,4701,14,4860,18,5020,21,5179,25,5338,28,5497,32,5657,35,5816,39,5975,43,6134,47,6294,50,6453,54,6612,58,6771,62,6931,65,7090,69,7249,73,7408,77,7568,79,7727,81,7886,82,8046,82,8205,83,8364,84,8523,85,8683,85,8842,86,9001,87,9160,88,9320,88,9479,89,9638,90,9797,91,9957,91,10116,92,10275,93,10434,94,10594,94,10753,95,10912,96,11072,96,11231,97,11390,98,11549,99,11709,99,11868,100,12027,101,12186,102,12346,102,12505,103,12664,104,12824,104,12984,104,13145,103,13306,102,13466,102,13627,101,13788,100,13949,99,14109,99,14270,98,14431,97,14592,96,14752,96,14913,95,15074,94,15234,94,15395,93,15556,92,15717,91,15877,91,16038,90,16199,89,16360,88,16520,88,16681,87,16842,86,17003,85,17163,85,17324,84,17485,83,17646,82,17806,82,17967,81,18128,79,18288,77,18449,73,18610,69,18771,65,18931,62,19092,58,19253,54,19414,50,19574,47,19735,43,19896,39,20057,35,20217,32,20378,28,20539,25,20700,21,20860,18,21021,14,21182,10,21342,7,21503,3]" Type="3" Size="3" Color="0" Angle="5" /></Layout></Component><Component id="1" name="In"><Layout name="In_Distribute_Four" Number="2" Position="[[0.42, 0.42, 0.15, 0.15], [0.42, 0.58, 0.15, 0.15], [0.58, 0.42, 0.15, 0.15], [0.58, 0.58, 0.15, 0.15]]" Uniformity="0"><Entity bbox="[0.58, 0.42, 0.15, 0.15]" real_bbox="[0.5594, 0.4188, 0.1125, 0.1187]" mask="[13028,1,13187,3,13347,3,13506,5,13666,5,13825,7,13984,9,14144,9,14303,11,14463,11,14622,13,14782,13,14941,15,15101,15,15260,17,15420,17,15579,19,15740,17]" Type="1" Size="5" Color="6" Angle="3" /><Entity bbox="[0.42, 0.58, 0.15, 0.15]" real_bbox="[0.4031, 0.575, 0.1125, 0.1187]" mask="[9053,1,9212,3,9372,3,9531,5,9691,5,9850,7,10009,9,10169,9,10328,11,10488,11,10647,13,10807,13,10966,15,11126,15,11285,17,11445,17,11604,19,11765,17]" Type="1" Size="5" Color="6" Angle="3" /><Entity bbox="[0.58, 0.58, 0.15, 0.15]" real_bbox="[0.5594, 0.575, 0.1125, 0.1187]" mask="[13053,1,13212,3,13372,3,13531,5,13691,5,13850,7,14009,9,14169,9,14328,11,14488,11,14647,13,14807,13,14966,15,15126,15,15285,17,15445,17,15604,19,15765,17]" Type="1" Size="5" Color="6" Angle="3" /></Layout></Component><Component id="2" name="Mesh"><Layout name="Mesh_Layout" Number="2" Position="[[0.08, 0.08, 0.5, 0.08], [0.5, 0.08, 0.92, 0.08], [0.5, 0.08, 0.5, 0.5], [0.92, 0.08, 0.92, 0.5], [0.92, 0.5, 0.92, 0.92], [0.5, 0.5, 0.92, 0.5], [0.5, 0.92, 0.92, 0.92], [0.08, 0.92, 0.5, 0.92], [0.5, 0.5, 0.5, 0.92], [0.08, 0.5, 0.08, 0.92], [0.08, 0.08, 0.08, 0.5], [0.08, 0.5, 0.5, 0.5]]" Uniformity="1"><Entity bbox="[0.5, 0.08, 0.5, 0.5]" real_bbox="[0.6503, -0.0753, 0.3193, 0.3193]" mask="[12653,69,12812,71,12973,69]" Type="6" Size="0" Color="0" Angle="0" /><Entity bbox="[0.08, 0.5, 0.5, 0.5]" real_bbox="[-0.0753, 0.3497, 0.3193, 0.3193]" mask="[1841,1,2000,3,2160,3,2320,3,2480,3,2640,3,2800,3,2960,3,3120,3,3280,3,3440,3,3600,3,3760,3,3920,3,4080,3,4240,3,4400,3,4560,3,4720,3,4880,3,5040,3,5200,3,5360,3,5520,3,5680,3,5840,3,6000,3,6160,3,6320,3,6480,3,6640,3,6800,3,6960,3,7120,3,7280,3,7440,3,7600,3,7760,3,7920,3,8080,3,8240,3,8400,3,8560,3,8720,3,8880,3,9040,3,9200,3,9360,3,9520,3,9680,3,9840,3,10000,3,10160,3,10320,3,10480,3,10640,3,10800,3,10960,3,11120,3,11280,3,11440,3,11600,3,11760,3,11920,3,12080,3,12240,3,12400,3,12560,3,12720,3,12880,3,13041,1]" Type="6" Size="0" Color="0" Angle="0" /><Entity bbox="[0.08, 0.08, 0.5, 0.08]" real_bbox="[-0.0753, -0.0753, 0.3193, 0.3193]" mask="[1773,1,1932,3,2092,3,2252,3,2412,3,2572,3,2732,3,2892,3,3052,3,3212,3,3372,3,3532,3,3692,3,3852,3,4012,3,4172,3,4332,3,4492,3,4652,3,4812,3,4972,3,5132,3,5292,3,5452,3,5612,3,5772,3,5932,3,6092,3,6252,3,6412,3,6572,3,6732,3,6892,3,7052,3,7212,3,7372,3,7532,3,7692,3,7852,3,8012,3,8172,3,8332,3,8492,3,8652,3,8812,3,8972,3,9132,3,9292,3,9452,3,9612,3,9772,3,9932,3,10092,3,10252,3,10412,3,10572,3,10732,3,10892,3,11052,3,11212,3,11372,3,11532,3,11692,3,11852,3,12012,3,12172,3,12332,3,12492,3,12652,3,12812,3,12973,1]" Type="6" Size="0" Color="0" Angle="0" /></Layout></Component></Struct></Panel><Panel><Struct name="Out_In"><Component id="0" name="Out"><Layout name="Out_Center_Single" Number="0" Position="[[0.5, 0.5, 1, 1]]" Uniformity="0"><Entity bbox="[0.5, 0.5, 1, 1]" real_bbox="[0.5, 0.4656, 0.6813, 0.65]" mask="[4223,3,4382,7,4542,10,4701,14,4860,18,5020,21,5179,25,5338,28,5497,32,5657,35,5816,39,5975,43,6134,47,6294,50,6453,54,6612,58,6771,62,6931,65,7090,69,7249,73,7408,77,7568,79,7727,81,7886,82,8046,82,8205,83,8364,84,8523,85,8683,85,8842,86,9001,87,9160,88,9320,88,9479,89,9638,90,9797,91,9957,91,10116,92,10275,93,10434,94,10594,94,10753,95,10912,96,11072,96,11231,97,11390,98,11549,99,11709,99,11868,100,12027,101,12186,102,12346,102,12505,103,12664,104,12824,104,12984,104,13145,103,13306,102,13466,102,13627,101,13788,100,13949,99,14109,99,14270,98,14431,97,14592,96,14752,96,14913,95,15074,94,15234,94,15395,93,15556,92,15717,91,15877,91,16038,90,16199,89,16360,88,16520,88,16681,87,16842,86,17003,85,17163,85,17324,84,17485,83,17646,82,17806,82,17967,81,18128,79,18288,77,18449,73,18610,69,18771,65,18931,62,19092,58,19253,54,19414,50,19574,47,19735,43,19896,39,20057,35,20217,32,20378,28,20539,25,20700,21,20860,18,21021,14,21182,10,21342,7,21503,3]" Type="3" Size="3" Color="0" Angle="5" /></Layout></Component><Component id="1" name="In"><Layout name="In_Distribute_Four" Number="0" Position="[[0.42, 0.42, 0.15, 0.15], [0.42, 0.58, 0.15, 0.15], [0.58, 0.42, 0.15, 0.15], [0.58, 0.58, 0.15, 0.15]]" Uniformity="0"><Entity bbox="[0.42, 0.58, 0.15, 0.15]" real_bbox="[0.4188, 0.575, 0.1063, 0.1063]" mask="[9526,15,9685,17,9845,17,10005,17,10165,17,10325,17,10485,17,10645,17,10805,17,10965,17,11125,17,11285,17,11445,17,11605,17,11765,17,11925,17,12086,15]" Type="2" Size="5" Color="6" Angle="3" /></Layout></Component><Component id="2" name="Mesh"><Layout name="Mesh_Layout" Number="2" Position="[[0.08, 0.08, 0.5, 0.08], [0.5, 0.08, 0.92, 0.08], [0.5, 0.08, 0.5, 0.5], [0.92, 0.08, 0.92, 0.5], [0.92, 0.5, 0.92, 0.92], [0.5, 0.5, 0.92, 0.5], [0.5, 0.92, 0.92, 0.92], [0.08, 0.92, 0.5, 0.92], [0.5, 0.5, 0.5, 0.92], [0.08, 0.5, 0.08, 0.92], [0.08, 0.08, 0.08, 0.5], [0.08, 0.5, 0.5, 0.5]]" Uniformity="1"><Entity bbox="[0.5, 0.08, 0.92, 0.08]" real_bbox="[0.3519, -0.0731, 0.3149, 0.3149]" mask="[12653,1,12812,3,12972,3,13132,3,13292,3,13452,3,13612,3,13772,3,13932,3,14092,3,14252,3,14412,3,14572,3,14732,3,14892,3,15052,3,15212,3,15372,3,15532,3,15692,3,15852,3,16012,3,16172,3,16332,3,16492,3,16652,3,16812,3,16972,3,17132,3,17292,3,17452,3,17612,3,17772,3,17932,3,18092,3,18252,3,18412,3,18572,3,18732,3,18892,3,19052,3,19212,3,19372,3,19532,3,19692,3,19852,3,20012,3,20172,3,20332,3,20492,3,20652,3,20812,3,20972,3,21132,3,21292,3,21452,3,21612,3,21772,3,21932,3,22092,3,22252,3,22412,3,22572,3,22732,3,22892,3,23052,3,23212,3,23372,3,23532,3,23693,1]" Type="6" Size="0" Color="0" Angle="0" /><Entity bbox="[0.92, 0.08, 0.92, 0.5]" real_bbox="[1.069, -0.0753, 0.3193, 0.3193]" mask="[23373,69,23532,71,23693,69]" Type="6" Size="0" Color="0" Angle="0" /><Entity bbox="[0.92, 0.5, 0.92, 0.92]" real_bbox="[1.0668, 0.3519, 0.3149, 0.3149]" mask="[23441,68,23600,70,23761,68]" Type="6" Size="0" Color="0" Angle="0" /></Layout></Component></Struct></Panel><Panel><Struct name="Out_In"><Component id="0" name="Out"><Layout name="Out_Center_Single" Number="0" Position="[[0.5, 0.5, 1, 1]]" Uniformity="0"><Entity bbox="[0.5, 0.5, 1, 1]" real_bbox="[0.5, 0.4656, 0.6813, 0.65]" mask="[4223,3,4382,7,4542,10,4701,14,4860,18,5020,21,5179,25,5338,28,5497,32,5657,35,5816,39,5975,43,6134,47,6294,50,6453,54,6612,58,6771,62,6931,65,7090,69,7249,73,7408,77,7568,79,7727,81,7886,82,8046,82,8205,83,8364,84,8523,85,8683,85,8842,86,9001,87,9160,88,9320,88,9479,89,9638,90,9797,91,9957,91,10116,92,10275,93,10434,94,10594,94,10753,95,10912,96,11072,96,11231,97,11390,98,11549,99,11709,99,11868,100,12027,101,12186,102,12346,102,12505,103,12664,104,12824,104,12984,104,13145,103,13306,102,13466,102,13627,101,13788,100,13949,99,14109,99,14270,98,14431,97,14592,96,14752,96,14913,95,15074,94,15234,94,15395,93,15556,92,15717,91,15877,91,16038,90,16199,89,16360,88,16520,88,16681,87,16842,86,17003,85,17163,85,17324,84,17485,83,17646,82,17806,82,17967,81,18128,79,18288,77,18449,73,18610,69,18771,65,18931,62,19092,58,19253,54,19414,50,19574,47,19735,43,19896,39,20057,35,20217,32,20378,28,20539,25,20700,21,20860,18,21021,14,21182,10,21342,7,21503,3]" Type="3" Size="3" Color="0" Angle="5" /></Layout></Component><Component id="1" name="In"><Layout name="In_Distribute_Four" Number="0" Position="[[0.42, 0.42, 0.15, 0.15], [0.42, 0.58, 0.15, 0.15], [0.58, 0.42, 0.15, 0.15], [0.58, 0.58, 0.15, 0.15]]" Uniformity="0"><Entity bbox="[0.42, 0.58, 0.15, 0.15]" real_bbox="[0.4188, 0.575, 0.1063, 0.1063]" mask="[9526,15,9685,17,9845,17,10005,17,10165,17,10325,17,10485,17,10645,17,10805,17,10965,17,11125,17,11285,17,11445,17,11605,17,11765,17,11925,17,12086,15]" Type="2" Size="5" Color="6" Angle="3" /></Layout></Component><Component id="2" name="Mesh"><Layout name="Mesh_Layout" Number="2" Position="[[0.08, 0.08, 0.5, 0.08], [0.5, 0.08, 0.92, 0.08], [0.5, 0.08, 0.5, 0.5], [0.92, 0.08, 0.92, 0.5], [0.92, 0.5, 0.92, 0.92], [0.5, 0.5, 0.92, 0.5], [0.5, 0.92, 0.92, 0.92], [0.08, 0.92, 0.5, 0.92], [0.5, 0.5, 0.5, 0.92], [0.08, 0.5, 0.08, 0.92], [0.08, 0.08, 0.08, 0.5], [0.08, 0.5, 0.5, 0.5]]" Uniformity="1"><Entity bbox="[0.5, 0.08, 0.5, 0.5]" real_bbox="[0.6503, -0.0753, 0.3193, 0.3193]" mask="[12653,69,12812,71,12973,69]" Type="6" Size="0" Color="0" Angle="0" /><Entity bbox="[0.08, 0.5, 0.5, 0.5]" real_bbox="[-0.0753, 0.3497, 0.3193, 0.3193]" mask="[1841,1,2000,3,2160,3,2320,3,2480,3,2640,3,2800,3,2960,3,3120,3,3280,3,3440,3,3600,3,3760,3,3920,3,4080,3,4240,3,4400,3,4560,3,4720,3,4880,3,5040,3,5200,3,5360,3,5520,3,5680,3,5840,3,6000,3,6160,3,6320,3,6480,3,6640,3,6800,3,6960,3,7120,3,7280,3,7440,3,7600,3,7760,3,7920,3,8080,3,8240,3,8400,3,8560,3,8720,3,8880,3,9040,3,9200,3,9360,3,9520,3,9680,3,9840,3,10000,3,10160,3,10320,3,10480,3,10640,3,10800,3,10960,3,11120,3,11280,3,11440,3,11600,3,11760,3,11920,3,12080,3,12240,3,12400,3,12560,3,12720,3,12880,3,13041,1]" Type="6" Size="0" Color="0" Angle="0" /><Entity bbox="[0.08, 0.08, 0.5, 0.08]" real_bbox="[-0.0753, -0.0753, 0.3193, 0.3193]" mask="[1773,1,1932,3,2092,3,2252,3,2412,3,2572,3,2732,3,2892,3,3052,3,3212,3,3372,3,3532,3,3692,3,3852,3,4012,3,4172,3,4332,3,4492,3,4652,3,4812,3,4972,3,5132,3,5292,3,5452,3,5612,3,5772,3,5932,3,6092,3,6252,3,6412,3,6572,3,6732,3,6892,3,7052,3,7212,3,7372,3,7532,3,7692,3,7852,3,8012,3,8172,3,8332,3,8492,3,8652,3,8812,3,8972,3,9132,3,9292,3,9452,3,9612,3,9772,3,9932,3,10092,3,10252,3,10412,3,10572,3,10732,3,10892,3,11052,3,11212,3,11372,3,11532,3,11692,3,11852,3,12012,3,12172,3,12332,3,12492,3,12652,3,12812,3,12973,1]" Type="6" Size="0" Color="0" Angle="0" /></Layout></Component></Struct></Panel><Panel><Struct name="Out_In"><Component id="0" name="Out"><Layout name="Out_Center_Single" Number="0" Position="[[0.5, 0.5, 1, 1]]" Uniformity="0"><Entity bbox="[0.5, 0.5, 1, 1]" real_bbox="[0.5, 0.4656, 0.6813, 0.65]" mask="[4223,3,4382,7,4542,10,4701,14,4860,18,5020,21,5179,25,5338,28,5497,32,5657,35,5816,39,5975,43,6134,47,6294,50,6453,54,6612,58,6771,62,6931,65,7090,69,7249,73,7408,77,7568,79,7727,81,7886,82,8046,82,8205,83,8364,84,8523,85,8683,85,8842,86,9001,87,9160,88,9320,88,9479,89,9638,90,9797,91,9957,91,10116,92,10275,93,10434,94,10594,94,10753,95,10912,96,11072,96,11231,97,11390,98,11549,99,11709,99,11868,100,12027,101,12186,102,12346,102,12505,103,12664,104,12824,104,12984,104,13145,103,13306,102,13466,102,13627,101,13788,100,13949,99,14109,99,14270,98,14431,97,14592,96,14752,96,14913,95,15074,94,15234,94,15395,93,15556,92,15717,91,15877,91,16038,90,16199,89,16360,88,16520,88,16681,87,16842,86,17003,85,17163,85,17324,84,17485,83,17646,82,17806,82,17967,81,18128,79,18288,77,18449,73,18610,69,18771,65,18931,62,19092,58,19253,54,19414,50,19574,47,19735,43,19896,39,20057,35,20217,32,20378,28,20539,25,20700,21,20860,18,21021,14,21182,10,21342,7,21503,3]" Type="3" Size="3" Color="0" Angle="5" /></Layout></Component><Component id="1" name="In"><Layout name="In_Distribute_Four" Number="0" Position="[[0.42, 0.42, 0.15, 0.15], [0.42, 0.58, 0.15, 0.15], [0.58, 0.42, 0.15, 0.15], [0.58, 0.58, 0.15, 0.15]]" Uniformity="0"><Entity bbox="[0.42, 0.58, 0.15, 0.15]" real_bbox="[0.4031, 0.575, 0.1125, 0.1187]" mask="[9053,1,9212,3,9372,3,9531,5,9691,5,9850,7,10009,9,10169,9,10328,11,10488,11,10647,13,10807,13,10966,15,11126,15,11285,17,11445,17,11604,19,11765,17]" Type="1" Size="5" Color="6" Angle="3" /></Layout></Component><Component id="2" name="Mesh"><Layout name="Mesh_Layout" Number="2" Position="[[0.08, 0.08, 0.5, 0.08], [0.5, 0.08, 0.92, 0.08], [0.5, 0.08, 0.5, 0.5], [0.92, 0.08, 0.92, 0.5], [0.92, 0.5, 0.92, 0.92], [0.5, 0.5, 0.92, 0.5], [0.5, 0.92, 0.92, 0.92], [0.08, 0.92, 0.5, 0.92], [0.5, 0.5, 0.5, 0.92], [0.08, 0.5, 0.08, 0.92], [0.08, 0.08, 0.08, 0.5], [0.08, 0.5, 0.5, 0.5]]" Uniformity="1"><Entity bbox="[0.5, 0.08, 0.5, 0.5]" real_bbox="[0.6503, -0.0753, 0.3193, 0.3193]" mask="[12653,69,12812,71,12973,69]" Type="6" Size="0" Color="0" Angle="0" /><Entity bbox="[0.08, 0.5, 0.5, 0.5]" real_bbox="[-0.0753, 0.3497, 0.3193, 0.3193]" mask="[1841,1,2000,3,2160,3,2320,3,2480,3,2640,3,2800,3,2960,3,3120,3,3280,3,3440,3,3600,3,3760,3,3920,3,4080,3,4240,3,4400,3,4560,3,4720,3,4880,3,5040,3,5200,3,5360,3,5520,3,5680,3,5840,3,6000,3,6160,3,6320,3,6480,3,6640,3,6800,3,6960,3,7120,3,7280,3,7440,3,7600,3,7760,3,7920,3,8080,3,8240,3,8400,3,8560,3,8720,3,8880,3,9040,3,9200,3,9360,3,9520,3,9680,3,9840,3,10000,3,10160,3,10320,3,10480,3,10640,3,10800,3,10960,3,11120,3,11280,3,11440,3,11600,3,11760,3,11920,3,12080,3,12240,3,12400,3,12560,3,12720,3,12880,3,13041,1]" Type="6" Size="0" Color="0" Angle="0" /><Entity bbox="[0.08, 0.08, 0.5, 0.08]" real_bbox="[-0.0753, -0.0753, 0.3193, 0.3193]" mask="[1773,1,1932,3,2092,3,2252,3,2412,3,2572,3,2732,3,2892,3,3052,3,3212,3,3372,3,3532,3,3692,3,3852,3,4012,3,4172,3,4332,3,4492,3,4652,3,4812,3,4972,3,5132,3,5292,3,5452,3,5612,3,5772,3,5932,3,6092,3,6252,3,6412,3,6572,3,6732,3,6892,3,7052,3,7212,3,7372,3,7532,3,7692,3,7852,3,8012,3,8172,3,8332,3,8492,3,8652,3,8812,3,8972,3,9132,3,9292,3,9452,3,9612,3,9772,3,9932,3,10092,3,10252,3,10412,3,10572,3,10732,3,10892,3,11052,3,11212,3,11372,3,11532,3,11692,3,11852,3,12012,3,12172,3,12332,3,12492,3,12652,3,12812,3,12973,1]" Type="6" Size="0" Color="0" Angle="0" /></Layout></Component></Struct></Panel><Panel><Struct name="Out_In"><Component id="0" name="Out"><Layout name="Out_Center_Single" Number="0" Position="[[0.5, 0.5, 1, 1]]" Uniformity="0"><Entity bbox="[0.5, 0.5, 1, 1]" real_bbox="[0.5, 0.4656, 0.6813, 0.65]" mask="[4223,3,4382,7,4542,10,4701,14,4860,18,5020,21,5179,25,5338,28,5497,32,5657,35,5816,39,5975,43,6134,47,6294,50,6453,54,6612,58,6771,62,6931,65,7090,69,7249,73,7408,77,7568,79,7727,81,7886,82,8046,82,8205,83,8364,84,8523,85,8683,85,8842,86,9001,87,9160,88,9320,88,9479,89,9638,90,9797,91,9957,91,10116,92,10275,93,10434,94,10594,94,10753,95,10912,96,11072,96,11231,97,11390,98,11549,99,11709,99,11868,100,12027,101,12186,102,12346,102,12505,103,12664,104,12824,104,12984,104,13145,103,13306,102,13466,102,13627,101,13788,100,13949,99,14109,99,14270,98,14431,97,14592,96,14752,96,14913,95,15074,94,15234,94,15395,93,15556,92,15717,91,15877,91,16038,90,16199,89,16360,88,16520,88,16681,87,16842,86,17003,85,17163,85,17324,84,17485,83,17646,82,17806,82,17967,81,18128,79,18288,77,18449,73,18610,69,18771,65,18931,62,19092,58,19253,54,19414,50,19574,47,19735,43,19896,39,20057,35,20217,32,20378,28,20539,25,20700,21,20860,18,21021,14,21182,10,21342,7,21503,3]" Type="3" Size="3" Color="0" Angle="5" /></Layout></Component><Component id="1" name="In"><Layout name="In_Distribute_Four" Number="2" Position="[[0.42, 0.42, 0.15, 0.15], [0.42, 0.58, 0.15, 0.15], [0.58, 0.42, 0.15, 0.15], [0.58, 0.58, 0.15, 0.15]]" Uniformity="0"><Entity bbox="[0.58, 0.42, 0.15, 0.15]" real_bbox="[0.5594, 0.4188, 0.1125, 0.1187]" mask="[13028,1,13187,3,13347,3,13506,5,13666,5,13825,7,13984,9,14144,9,14303,11,14463,11,14622,13,14782,13,14941,15,15101,15,15260,17,15420,17,15579,19,15740,17]" Type="1" Size="5" Color="6" Angle="3" /><Entity bbox="[0.42, 0.58, 0.15, 0.15]" real_bbox="[0.4031, 0.575, 0.1125, 0.1187]" mask="[9053,1,9212,3,9372,3,9531,5,9691,5,9850,7,10009,9,10169,9,10328,11,10488,11,10647,13,10807,13,10966,15,11126,15,11285,17,11445,17,11604,19,11765,17]" Type="1" Size="5" Color="6" Angle="3" /><Entity bbox="[0.58, 0.58, 0.15, 0.15]" real_bbox="[0.5594, 0.575, 0.1125, 0.1187]" mask="[13053,1,13212,3,13372,3,13531,5,13691,5,13850,7,14009,9,14169,9,14328,11,14488,11,14647,13,14807,13,14966,15,15126,15,15285,17,15445,17,15604,19,15765,17]" Type="1" Size="5" Color="6" Angle="3" /></Layout></Component><Component id="2" name="Mesh"><Layout name="Mesh_Layout" Number="2" Position="[[0.08, 0.08, 0.5, 0.08], [0.5, 0.08, 0.92, 0.08], [0.5, 0.08, 0.5, 0.5], [0.92, 0.08, 0.92, 0.5], [0.92, 0.5, 0.92, 0.92], [0.5, 0.5, 0.92, 0.5], [0.5, 0.92, 0.92, 0.92], [0.08, 0.92, 0.5, 0.92], [0.5, 0.5, 0.5, 0.92], [0.08, 0.5, 0.08, 0.92], [0.08, 0.08, 0.08, 0.5], [0.08, 0.5, 0.5, 0.5]]" Uniformity="1"><Entity bbox="[0.5, 0.08, 0.92, 0.08]" real_bbox="[0.3519, -0.0731, 0.3149, 0.3149]" mask="[12653,1,12812,3,12972,3,13132,3,13292,3,13452,3,13612,3,13772,3,13932,3,14092,3,14252,3,14412,3,14572,3,14732,3,14892,3,15052,3,15212,3,15372,3,15532,3,15692,3,15852,3,16012,3,16172,3,16332,3,16492,3,16652,3,16812,3,16972,3,17132,3,17292,3,17452,3,17612,3,17772,3,17932,3,18092,3,18252,3,18412,3,18572,3,18732,3,18892,3,19052,3,19212,3,19372,3,19532,3,19692,3,19852,3,20012,3,20172,3,20332,3,20492,3,20652,3,20812,3,20972,3,21132,3,21292,3,21452,3,21612,3,21772,3,21932,3,22092,3,22252,3,22412,3,22572,3,22732,3,22892,3,23052,3,23212,3,23372,3,23532,3,23693,1]" Type="6" Size="0" Color="0" Angle="0" /><Entity bbox="[0.92, 0.08, 0.92, 0.5]" real_bbox="[1.069, -0.0753, 0.3193, 0.3193]" mask="[23373,69,23532,71,23693,69]" Type="6" Size="0" Color="0" Angle="0" /><Entity bbox="[0.92, 0.5, 0.92, 0.92]" real_bbox="[1.0668, 0.3519, 0.3149, 0.3149]" mask="[23441,68,23600,70,23761,68]" Type="6" Size="0" Color="0" Angle="0" /></Layout></Component></Struct></Panel><Panel><Struct name="Out_In"><Component id="0" name="Out"><Layout name="Out_Center_Single" Number="0" Position="[[0.5, 0.5, 1, 1]]" Uniformity="0"><Entity bbox="[0.5, 0.5, 1, 1]" real_bbox="[0.5, 0.4656, 0.6813, 0.65]" mask="[4223,3,4382,7,4542,10,4701,14,4860,18,5020,21,5179,25,5338,28,5497,32,5657,35,5816,39,5975,43,6134,47,6294,50,6453,54,6612,58,6771,62,6931,65,7090,69,7249,73,7408,77,7568,79,7727,81,7886,82,8046,82,8205,83,8364,84,8523,85,8683,85,8842,86,9001,87,9160,88,9320,88,9479,89,9638,90,9797,91,9957,91,10116,92,10275,93,10434,94,10594,94,10753,95,10912,96,11072,96,11231,97,11390,98,11549,99,11709,99,11868,100,12027,101,12186,102,12346,102,12505,103,12664,104,12824,104,12984,104,13145,103,13306,102,13466,102,13627,101,13788,100,13949,99,14109,99,14270,98,14431,97,14592,96,14752,96,14913,95,15074,94,15234,94,15395,93,15556,92,15717,91,15877,91,16038,90,16199,89,16360,88,16520,88,16681,87,16842,86,17003,85,17163,85,17324,84,17485,83,17646,82,17806,82,17967,81,18128,79,18288,77,18449,73,18610,69,18771,65,18931,62,19092,58,19253,54,19414,50,19574,47,19735,43,19896,39,20057,35,20217,32,20378,28,20539,25,20700,21,20860,18,21021,14,21182,10,21342,7,21503,3]" Type="3" Size="3" Color="0" Angle="5" /></Layout></Component><Component id="1" name="In"><Layout name="In_Distribute_Four" Number="0" Position="[[0.42, 0.42, 0.15, 0.15], [0.42, 0.58, 0.15, 0.15], [0.58, 0.42, 0.15, 0.15], [0.58, 0.58, 0.15, 0.15]]" Uniformity="0"><Entity bbox="[0.42, 0.58, 0.15, 0.15]" real_bbox="[0.4031, 0.575, 0.1125, 0.1187]" mask="[9053,1,9212,3,9372,3,9531,5,9691,5,9850,7,10009,9,10169,9,10328,11,10488,11,10647,13,10807,13,10966,15,11126,15,11285,17,11445,17,11604,19,11765,17]" Type="1" Size="5" Color="6" Angle="3" /></Layout></Component><Component id="2" name="Mesh"><Layout name="Mesh_Layout" Number="2" Position="[[0.08, 0.08, 0.5, 0.08], [0.5, 0.08, 0.92, 0.08], [0.5, 0.08, 0.5, 0.5], [0.92, 0.08, 0.92, 0.5], [0.92, 0.5, 0.92, 0.92], [0.5, 0.5, 0.92, 0.5], [0.5, 0.92, 0.92, 0.92], [0.08, 0.92, 0.5, 0.92], [0.5, 0.5, 0.5, 0.92], [0.08, 0.5, 0.08, 0.92], [0.08, 0.08, 0.08, 0.5], [0.08, 0.5, 0.5, 0.5]]" Uniformity="1"><Entity bbox="[0.5, 0.08, 0.92, 0.08]" real_bbox="[0.3519, -0.0731, 0.3149, 0.3149]" mask="[12653,1,12812,3,12972,3,13132,3,13292,3,13452,3,13612,3,13772,3,13932,3,14092,3,14252,3,14412,3,14572,3,14732,3,14892,3,15052,3,15212,3,15372,3,15532,3,15692,3,15852,3,16012,3,16172,3,16332,3,16492,3,16652,3,16812,3,16972,3,17132,3,17292,3,17452,3,17612,3,17772,3,17932,3,18092,3,18252,3,18412,3,18572,3,18732,3,18892,3,19052,3,19212,3,19372,3,19532,3,19692,3,19852,3,20012,3,20172,3,20332,3,20492,3,20652,3,20812,3,20972,3,21132,3,21292,3,21452,3,21612,3,21772,3,21932,3,22092,3,22252,3,22412,3,22572,3,22732,3,22892,3,23052,3,23212,3,23372,3,23532,3,23693,1]" Type="6" Size="0" Color="0" Angle="0" /><Entity bbox="[0.92, 0.08, 0.92, 0.5]" real_bbox="[1.069, -0.0753, 0.3193, 0.3193]" mask="[23373,69,23532,71,23693,69]" Type="6" Size="0" Color="0" Angle="0" /><Entity bbox="[0.92, 0.5, 0.92, 0.92]" real_bbox="[1.0668, 0.3519, 0.3149, 0.3149]" mask="[23441,68,23600,70,23761,68]" Type="6" Size="0" Color="0" Angle="0" /></Layout></Component></Struct></Panel></Panels><Rules><Rule_Group id="0"><Rule name="Constant" attr="Number/Position" /><Rule name="Progression" attr="Type" /><Rule name="Progression" attr="Size" /><Rule name="Constant" attr="Color" /></Rule_Group><Rule_Group id="1"><Rule name="Distribute_Three" attr="Position" /><Rule name="Constant" attr="Type" /><Rule name="Arithmetic" attr="Size" /><Rule name="Progression" attr="Color" /></Rule_Group><Rule_Group id="2"><Rule name="Distribute_Three" attr="Position" /><Rule name="Constant" attr="Type" /><Rule name="Constant" attr="Size" /><Rule name="Constant" attr="Color" /></Rule_Group></Rules><Modified_attributes><Candidate id="0"><Attribute component_id="2" name="Position" /><Attribute component_id="1" name="Type" /><Attribute component_id="1" name="Number" /></Candidate><Candidate id="1"><Attribute component_id="1" name="Type" /><Attribute component_id="1" name="Number" /></Candidate><Candidate id="2"><Attribute component_id="1" name="Number" /></Candidate><Candidate id="3"><Attribute component_id="2" name="Position" /><Attribute component_id="1" name="Type" /></Candidate><Candidate id="4"><Attribute component_id="1" name="Type" /></Candidate><Candidate id="5" /><Candidate id="6"><Attribute component_id="2" name="Position" /><Attribute component_id="1" name="Number" /></Candidate><Candidate id="7"><Attribute component_id="2" name="Position" /></Candidate></Modified_attributes></Data>