<Data><Panels><Panel><Struct name="Left_Right"><Component id="0" name="Left"><Layout name="Left_Center_Single" Number="0" Position="[[0.5, 0.25, 0.5, 0.5]]" Uniformity="0"><Entity bbox="[0.5, 0.25, 0.5, 0.5]" real_bbox="[0.5, 0.25, 0.2688, 0.2688]" mask="[9319,1,9321,1,9323,1,9474,1,9476,1,9479,1,9481,1,9483,1,9486,1,9488,1,9632,1,9634,1,9636,2,9639,5,9645,2,9648,1,9650,1,9789,1,9791,1,9793,1,9809,1,9811,1,9813,1,9948,1,9950,1,9972,1,9974,1,10107,1,10109,25,10135,1,10266,1,10268,27,10296,1,10425,1,10427,29,10457,1,10584,1,10586,31,10618,1,10743,1,10745,33,10779,1,10902,1,10904,35,10940,1,11063,1,11099,1,11222,1,11260,1,11381,1,11383,37,11421,1,11541,1,11543,37,11581,1,11700,1,11702,39,11742,1,11861,1,11901,1,12020,1,12062,1,12179,1,12181,41,12223,1,12340,1,12342,39,12382,1,12499,1,12501,41,12543,1,12659,1,12661,41,12703,1,12819,1,12863,1,12979,1,12981,41,13023,1,13139,1,13141,41,13183,1,13300,1,13302,39,13342,1,13460,1,13502,1,13620,1,13662,1,13781,1,13821,1,13940,1,13942,39,13982,1,14101,1,14103,37,14141,1,14261,1,14263,37,14301,1,14422,1,14460,1,14583,1,14619,1,14742,1,14744,35,14780,1,14903,1,14905,33,14939,1,15064,1,15066,31,15098,1,15225,1,15227,29,15257,1,15386,1,15388,27,15416,1,15547,1,15549,25,15575,1,15708,1,15710,1,15732,1,15734,1,15869,1,15871,1,15873,1,15889,1,15891,1,15893,1,16032,1,16034,1,16036,2,16039,5,16045,2,16048,1,16050,1,16194,1,16196,1,16198,1,16200,1,16202,1,16204,1,16206,1,16208,1,16357,1,16359,1,16361,1,16363,1,16365,1]" Type="5" Size="1" Color="2" Angle="2" /></Layout></Component><Component id="1" name="Right"><Layout name="Right_Center_Single" Number="0" Position="[[0.5, 0.75, 0.5, 0.5]]" Uniformity="3"><Entity bbox="[0.5, 0.75, 0.5, 0.5]" real_bbox="[0.5, 0.75, 0.3988, 0.3988]" mask="[7793,1,7795,1,7797,1,7952,1,7955,1,7957,1,7959,1,7961,1,8111,1,8118,1,8120,1,8122,1,8124,146,8271,13,8285,1,8287,1,8289,140,8430,16,8447,1,8449,1,8451,1,8588,1,8611,1,8613,1,8615,1,8617,130,8748,27,8776,1,8778,1,8780,1,8906,1,8939,1,8941,1,8943,1,8945,120,9066,37,9104,1,9106,118,9225,40,9266,1,9383,1,9425,1,9542,1,9586,1,9701,1,9746,1,9860,1,9906,1,9908,111,10020,46,10067,111,10179,48,10228,109,10338,49,10388,108,10497,51,10549,106,10656,51,10708,106,10815,53,10869,104,10974,54,11029,103,11133,55,11189,102,11292,56,11349,1,11450,1,11509,1,11609,1,11669,1,11769,1,11830,1,11929,1,11931,58,11990,1,12090,1,12149,1,12151,98,12250,1,12310,1,12410,1,12412,58,12471,99,12571,60,12632,99,12732,59,12792,98,12891,1,12951,1,12953,98,13052,59,13112,99,13212,60,13273,99,13373,58,13432,1,13532,1,13592,1,13594,98,13693,1,13752,1,13852,1,13854,58,13913,1,14012,1,14073,1,14173,1,14233,1,14333,1,14392,1,14493,1,14495,56,14552,102,14655,55,14711,103,14815,54,14870,104,14975,53,15029,106,15136,51,15188,106,15295,51,15347,108,15456,49,15506,109,15616,48,15665,111,15777,46,15824,111,15936,1,15982,1,16096,1,16141,1,16256,1,16300,1,16417,1,16459,1,16576,1,16578,40,16619,118,16738,1,16740,37,16778,120,16899,1,16901,1,16903,1,16936,1,17062,1,17064,1,17066,1,17068,27,17096,130,17227,1,17229,1,17231,1,17254,1,17391,1,17393,1,17395,1,17397,16,17414,140,17555,1,17557,1,17559,13,17573,146,17720,1,17722,1,17724,1,17731,1,17881,1,17883,1,17885,1,17887,1,17890,1,18045,1,18047,1,18049,1]" Type="4" Size="4" Color="2" Angle="2" /></Layout></Component><Component id="2" name="Mesh"><Layout name="Mesh_Layout" Number="2" Position="[[0.08, 0.08, 0.5, 0.08], [0.5, 0.08, 0.92, 0.08], [0.5, 0.08, 0.5, 0.5], [0.92, 0.08, 0.92, 0.5], [0.92, 0.5, 0.92, 0.92], [0.5, 0.5, 0.92, 0.5], [0.5, 0.92, 0.92, 0.92], [0.08, 0.92, 0.5, 0.92], [0.5, 0.5, 0.5, 0.92], [0.08, 0.5, 0.08, 0.92], [0.08, 0.08, 0.08, 0.5], [0.08, 0.5, 0.5, 0.5]]" Uniformity="0"><Entity bbox="[0.5, 0.08, 0.92, 0.08]" real_bbox="[0.3519, -0.0731, 0.3149, 0.3149]" mask="[12653,1,12812,3,12972,3,13132,3,13292,3,13452,3,13612,3,13772,3,13932,3,14092,3,14252,3,14412,3,14572,3,14732,3,14892,3,15052,3,15212,3,15372,3,15532,3,15692,3,15852,3,16012,3,16172,3,16332,3,16492,3,16652,3,16812,3,16972,3,17132,3,17292,3,17452,3,17612,3,17772,3,17932,3,18092,3,18252,3,18412,3,18572,3,18732,3,18892,3,19052,3,19212,3,19372,3,19532,3,19692,3,19852,3,20012,3,20172,3,20332,3,20492,3,20652,3,20812,3,20972,3,21132,3,21292,3,21452,3,21612,3,21772,3,21932,3,22092,3,22252,3,22412,3,22572,3,22732,3,22892,3,23052,3,23212,3,23372,3,23532,3,23693,1]" Type="6" Size="0" Color="0" Angle="0" /><Entity bbox="[0.5, 0.92, 0.92, 0.92]" real_bbox="[0.3519, 0.7707, 0.3149, 0.3149]" mask="[12788,1,12947,3,13107,3,13267,3,13427,3,13587,3,13747,3,13907,3,14067,3,14227,3,14387,3,14547,3,14707,3,14867,3,15027,3,15187,3,15347,3,15507,3,15667,3,15827,3,15987,3,16147,3,16307,3,16467,3,16627,3,16787,3,16947,3,17107,3,17267,3,17427,3,17587,3,17747,3,17907,3,18067,3,18227,3,18387,3,18547,3,18707,3,18867,3,19027,3,19187,3,19347,3,19507,3,19667,3,19827,3,19987,3,20147,3,20307,3,20467,3,20627,3,20787,3,20947,3,21107,3,21267,3,21427,3,21587,3,21747,3,21907,3,22067,3,22227,3,22387,3,22547,3,22707,3,22867,3,23027,3,23187,3,23347,3,23507,3,23667,3,23828,1]" Type="6" Size="0" Color="0" Angle="0" /><Entity bbox="[0.5, 0.08, 0.5, 0.5]" real_bbox="[0.6503, -0.0753, 0.3193, 0.3193]" mask="[12653,69,12812,71,12973,69]" Type="6" Size="0" Color="0" Angle="0" /></Layout></Component></Struct></Panel><Panel><Struct name="Left_Right"><Component id="0" name="Left"><Layout name="Left_Center_Single" Number="0" Position="[[0.5, 0.25, 0.5, 0.5]]" Uniformity="0"><Entity bbox="[0.5, 0.25, 0.5, 0.5]" real_bbox="[0.5, 0.25, 0.2662, 0.2662]" mask="[9480,1,9482,1,9639,1,9641,1,9643,1,9798,1,9804,1,9957,1,9965,1,10116,1,10126,1,10275,1,10287,1,10434,1,10448,1,10593,1,10609,1,10752,1,10770,1,10911,1,10931,1,11070,1,11092,1,11229,1,11253,1,11388,1,11414,1,11547,1,11575,1,11706,1,11736,1,11865,1,11897,1,12024,1,12058,1,12183,1,12219,1,12342,1,12380,1,12501,1,12541,1,12660,1,12702,1,12820,1,12822,39,12862,1,12980,1,13022,1,13141,1,13181,1,13302,1,13340,1,13463,1,13499,1,13624,1,13658,1,13785,1,13817,1,13946,1,13976,1,14107,1,14135,1,14268,1,14294,1,14429,1,14453,1,14590,1,14612,1,14751,1,14771,1,14912,1,14930,1,15073,1,15089,1,15234,1,15248,1,15395,1,15407,1,15556,1,15566,1,15717,1,15725,1,15878,1,15884,1,16039,1,16041,1,16043,1,16200,1,16202,1]" Type="2" Size="1" Color="2" Angle="2" /></Layout></Component><Component id="1" name="Right"><Layout name="Right_Center_Single" Number="0" Position="[[0.5, 0.75, 0.5, 0.5]]" Uniformity="3"><Entity bbox="[0.5, 0.75, 0.5, 0.5]" real_bbox="[0.5088, 0.7412, 0.3811, 0.3811]" mask="[8106,1,8265,1,8267,1,8269,1,8271,1,8273,1,8424,1,8426,3,8430,1,8432,1,8434,1,8436,1,8438,1,8441,1,8444,1,8584,1,8586,8,8595,4,8600,1,8602,1,8604,1,8606,1,8608,1,8610,134,8745,20,8766,1,8768,1,8770,1,8772,1,8774,1,8903,1,8930,1,8933,1,8935,1,8937,1,8939,1,8941,2,8944,1,9063,1,9100,1,9103,1,9105,1,9222,1,9265,1,9267,115,9383,1,9425,1,9542,1,9585,1,9587,114,9702,43,9746,1,9861,1,9905,1,10020,1,10066,1,10179,1,10226,1,10339,1,10341,45,10387,111,10499,1,10546,1,10658,1,10706,1,10818,1,10867,1,10977,1,11026,1,11028,108,11137,1,11187,1,11296,1,11298,49,11348,107,11456,1,11506,1,11508,107,11616,1,11667,1,11669,106,11776,51,11828,106,11935,1,11987,1,11989,105,12095,53,12149,104,12254,53,12308,1,12413,1,12468,1,12470,102,12573,1,12628,1,12731,1,12733,55,12789,103,12893,55,12949,1,13051,1,13108,1,13210,1,13268,1,13370,1,13372,57,13430,99,13530,1,13589,1,13690,1,13749,1,13849,1,13851,58,13910,100,14011,1,14068,1,14070,101,14172,1,14229,1,14231,101,14333,1,14389,1,14391,102,14494,1,14550,1,14654,1,14656,53,14710,1,14815,1,14817,52,14870,106,14977,1,15030,1,15137,1,15139,51,15191,107,15299,1,15350,1,15352,107,15460,1,15508,1,15510,1,15620,1,15622,45,15668,1,15670,111,15782,1,15823,1,15825,1,15827,115,15943,1,15982,1,15984,1,16103,1,16105,35,16141,1,16264,1,16266,31,16298,1,16300,125,16426,1,16456,1,16458,1,16586,1,16588,26,16615,1,16617,130,16748,1,16771,1,16773,1,16908,1,16910,19,16930,1,16932,1,17069,1,17071,16,17088,1,17090,1,17230,1,17232,14,17247,1,17391,1,17393,10,17404,2,17552,1,17554,7,17562,1,17564,149,17714,1,17718,1,17720,1,17722,1,17874,1,17876,1,17878,1,17880,155,18036,1,18038]" Type="3" Size="4" Color="3" Angle="2" /></Layout></Component><Component id="2" name="Mesh"><Layout name="Mesh_Layout" Number="2" Position="[[0.08, 0.08, 0.5, 0.08], [0.5, 0.08, 0.92, 0.08], [0.5, 0.08, 0.5, 0.5], [0.92, 0.08, 0.92, 0.5], [0.92, 0.5, 0.92, 0.92], [0.5, 0.5, 0.92, 0.5], [0.5, 0.92, 0.92, 0.92], [0.08, 0.92, 0.5, 0.92], [0.5, 0.5, 0.5, 0.92], [0.08, 0.5, 0.08, 0.92], [0.08, 0.08, 0.08, 0.5], [0.08, 0.5, 0.5, 0.5]]" Uniformity="0"><Entity bbox="[0.5, 0.08, 0.92, 0.08]" real_bbox="[0.3519, -0.0731, 0.3149, 0.3149]" mask="[12653,1,12812,3,12972,3,13132,3,13292,3,13452,3,13612,3,13772,3,13932,3,14092,3,14252,3,14412,3,14572,3,14732,3,14892,3,15052,3,15212,3,15372,3,15532,3,15692,3,15852,3,16012,3,16172,3,16332,3,16492,3,16652,3,16812,3,16972,3,17132,3,17292,3,17452,3,17612,3,17772,3,17932,3,18092,3,18252,3,18412,3,18572,3,18732,3,18892,3,19052,3,19212,3,19372,3,19532,3,19692,3,19852,3,20012,3,20172,3,20332,3,20492,3,20652,3,20812,3,20972,3,21132,3,21292,3,21452,3,21612,3,21772,3,21932,3,22092,3,22252,3,22412,3,22572,3,22732,3,22892,3,23052,3,23212,3,23372,3,23532,3,23693,1]" Type="6" Size="0" Color="0" Angle="0" /><Entity bbox="[0.5, 0.92, 0.92, 0.92]" real_bbox="[0.3519, 0.7707, 0.3149, 0.3149]" mask="[12788,1,12947,3,13107,3,13267,3,13427,3,13587,3,13747,3,13907,3,14067,3,14227,3,14387,3,14547,3,14707,3,14867,3,15027,3,15187,3,15347,3,15507,3,15667,3,15827,3,15987,3,16147,3,16307,3,16467,3,16627,3,16787,3,16947,3,17107,3,17267,3,17427,3,17587,3,17747,3,17907,3,18067,3,18227,3,18387,3,18547,3,18707,3,18867,3,19027,3,19187,3,19347,3,19507,3,19667,3,19827,3,19987,3,20147,3,20307,3,20467,3,20627,3,20787,3,20947,3,21107,3,21267,3,21427,3,21587,3,21747,3,21907,3,22067,3,22227,3,22387,3,22547,3,22707,3,22867,3,23027,3,23187,3,23347,3,23507,3,23667,3,23828,1]" Type="6" Size="0" Color="0" Angle="0" /><Entity bbox="[0.5, 0.08, 0.5, 0.5]" real_bbox="[0.6503, -0.0753, 0.3193, 0.3193]" mask="[12653,69,12812,71,12973,69]" Type="6" Size="0" Color="0" Angle="0" /></Layout></Component></Struct></Panel><Panel><Struct name="Left_Right"><Component id="0" name="Left"><Layout name="Left_Center_Single" Number="0" Position="[[0.5, 0.25, 0.5, 0.5]]" Uniformity="0"><Entity bbox="[0.5, 0.25, 0.5, 0.5]" real_bbox="[0.5155, 0.2345, 0.2265, 0.2265]" mask="[10296,1,10451,1,10453,1,10455,1,10457,1,10608,1,10610,1,10612,1,10614,2,10617,146,10764,2,10767,1,10769,7,10777,144,10922,1,10924,1,10926,9,10936,141,11078,1,11080,1,11082,1,11095,1,11097,136,11234,1,11237,1,11239,17,11257,132,11390,1,11392,1,11394,1,11415,1,11545,1,11547,1,11549,1,11551,1,11553,22,11576,127,11704,1,11706,1,11708,1,11734,1,11736,125,11862,1,11864,1,11894,1,12021,1,12054,1,12181,1,12213,1,12342,1,12373,1,12503,1,12533,1,12535,129,12665,27,12693,1,12825,1,12853,1,12986,1,13012,1,13147,1,13172,1,13308,1,13331,1,13333,136,13470,21,13492,1,13630,1,13651,1,13791,1,13811,1,13952,1,13970,1,14113,1,14130,1,14132,142,14275,14,14290,1,14435,1,14450,1,14596,1,14609,1,14757,1,14769,1,14771,147,14919,9,14929,1,15079,1,15088,1,15090,150,15241,7,15249,152,15402,6,15409,1,15562,1,15567,1,15569,154,15724,4,15729,155,15885,2,15888,157,16046,1,16048]" Type="1" Size="1" Color="2" Angle="2" /></Layout></Component><Component id="1" name="Right"><Layout name="Right_Center_Single" Number="0" Position="[[0.5, 0.75, 0.5, 0.5]]" Uniformity="3"><Entity bbox="[0.5, 0.75, 0.5, 0.5]" real_bbox="[0.5243, 0.7257, 0.3502, 0.3502]" mask="[9103,1,9105,1,9257,1,9259,1,9261,1,9263,2,9266,149,9416,1,9418,1,9425,1,9571,1,9573,1,9575,1,9577,7,9585,142,9728,1,9730,1,9732,1,9744,1,9885,1,9887,2,9904,1,10041,1,10043,1,10045,1,10047,17,10065,132,10198,1,10200,1,10202,21,10224,128,10353,1,10355,1,10357,1,10359,24,10384,1,10510,1,10512,1,10514,1,10516,1,10542,1,10544,120,10665,2,10668,1,10670,1,10703,1,10822,2,10825,1,10827,1,10862,1,10980,1,10982,1,10984,38,11023,111,11135,2,11138,1,11140,41,11182,110,11293,1,11295,1,11297,1,11341,1,11343,107,11451,1,11453,1,11501,1,11609,1,11611,50,11662,107,11770,50,11821,109,11931,49,11981,1,12091,1,12139,1,12141,111,12253,47,12301,112,12414,45,12460,114,12575,44,12620,115,12736,43,12780,116,12897,41,12939,1,13057,1,13098,1,13218,1,13258,1,13379,1,13417,1,13419,121,13541,36,13578,1,13701,1,13736,1,13738,124,13863,34,13898,125,14024,32,14057,127,14185,31,14217,1,14345,1,14376,1,14378,128,14507,29,14537,130,14668,27,14696,1,14828,1,14855,1,14989,1,15015,1,15150,1,15174,1,15176,135,15312,22,15335,137,15473,21,15495,138,15634,20,15655,1,15794,1,15813,1,15815,140,15956,17,15974,1,16116,1,16133,1,16277,1,16293,1,16438,1,16452,1,16599,1,16612,1,16760,1,16771,1,16773,148,16922,9,16932,150,17083,8,17092,151,17244,7,17252,1,17404,1,17410,1,17412,153,17566,5,17572,154,17727,3,17731,156,17888,1,17890,1,18048,1,18050]" Type="1" Size="4" Color="4" Angle="2" /></Layout></Component><Component id="2" name="Mesh"><Layout name="Mesh_Layout" Number="2" Position="[[0.08, 0.08, 0.5, 0.08], [0.5, 0.08, 0.92, 0.08], [0.5, 0.08, 0.5, 0.5], [0.92, 0.08, 0.92, 0.5], [0.92, 0.5, 0.92, 0.92], [0.5, 0.5, 0.92, 0.5], [0.5, 0.92, 0.92, 0.92], [0.08, 0.92, 0.5, 0.92], [0.5, 0.5, 0.5, 0.92], [0.08, 0.5, 0.08, 0.92], [0.08, 0.08, 0.08, 0.5], [0.08, 0.5, 0.5, 0.5]]" Uniformity="0"><Entity bbox="[0.5, 0.08, 0.92, 0.08]" real_bbox="[0.3519, -0.0731, 0.3149, 0.3149]" mask="[12653,1,12812,3,12972,3,13132,3,13292,3,13452,3,13612,3,13772,3,13932,3,14092,3,14252,3,14412,3,14572,3,14732,3,14892,3,15052,3,15212,3,15372,3,15532,3,15692,3,15852,3,16012,3,16172,3,16332,3,16492,3,16652,3,16812,3,16972,3,17132,3,17292,3,17452,3,17612,3,17772,3,17932,3,18092,3,18252,3,18412,3,18572,3,18732,3,18892,3,19052,3,19212,3,19372,3,19532,3,19692,3,19852,3,20012,3,20172,3,20332,3,20492,3,20652,3,20812,3,20972,3,21132,3,21292,3,21452,3,21612,3,21772,3,21932,3,22092,3,22252,3,22412,3,22572,3,22732,3,22892,3,23052,3,23212,3,23372,3,23532,3,23693,1]" Type="6" Size="0" Color="0" Angle="0" /><Entity bbox="[0.5, 0.92, 0.92, 0.92]" real_bbox="[0.3519, 0.7707, 0.3149, 0.3149]" mask="[12788,1,12947,3,13107,3,13267,3,13427,3,13587,3,13747,3,13907,3,14067,3,14227,3,14387,3,14547,3,14707,3,14867,3,15027,3,15187,3,15347,3,15507,3,15667,3,15827,3,15987,3,16147,3,16307,3,16467,3,16627,3,16787,3,16947,3,17107,3,17267,3,17427,3,17587,3,17747,3,17907,3,18067,3,18227,3,18387,3,18547,3,18707,3,18867,3,19027,3,19187,3,19347,3,19507,3,19667,3,19827,3,19987,3,20147,3,20307,3,20467,3,20627,3,20787,3,20947,3,21107,3,21267,3,21427,3,21587,3,21747,3,21907,3,22067,3,22227,3,22387,3,22547,3,22707,3,22867,3,23027,3,23187,3,23347,3,23507,3,23667,3,23828,1]" Type="6" Size="0" Color="0" Angle="0" /><Entity bbox="[0.5, 0.08, 0.5, 0.5]" real_bbox="[0.6503, -0.0753, 0.3193, 0.3193]" mask="[12653,69,12812,71,12973,69]" Type="6" Size="0" Color="0" Angle="0" /></Layout></Component></Struct></Panel><Panel><Struct name="Left_Right"><Component id="0" name="Left"><Layout name="Left_Center_Single" Number="0" Position="[[0.5, 0.25, 0.5, 0.5]]" Uniformity="0"><Entity bbox="[0.5, 0.25, 0.5, 0.5]" real_bbox="[0.5, 0.25, 0.3546, 0.3546]" mask="[8360,1,8362,1,8519,1,8521,1,8523,1,8678,1,8684,1,8837,1,8845,1,8996,1,9006,1,9155,1,9167,1,9314,1,9328,1,9473,1,9489,1,9632,1,9650,1,9791,1,9811,1,9950,1,9972,1,10109,1,10133,1,10268,1,10294,1,10427,1,10455,1,10586,1,10616,1,10745,1,10777,1,10904,1,10938,1,11063,1,11099,1,11222,1,11260,1,11381,1,11421,1,11540,1,11582,1,11699,1,11743,1,11858,1,11904,1,12017,1,12065,1,12176,1,12226,1,12335,1,12387,1,12494,1,12548,1,12653,1,12709,1,12813,1,12815,53,12869,1,12973,1,13029,1,13134,1,13188,1,13295,1,13347,1,13456,1,13506,1,13617,1,13665,1,13778,1,13824,1,13939,1,13983,1,14100,1,14142,1,14261,1,14301,1,14422,1,14460,1,14583,1,14619,1,14744,1,14778,1,14905,1,14937,1,15066,1,15096,1,15227,1,15255,1,15388,1,15414,1,15549,1,15573,1,15710,1,15732,1,15871,1,15891,1,16032,1,16050,1,16193,1,16209,1,16354,1,16368,1,16515,1,16527,1,16676,1,16686,1,16837,1,16845,1,16998,1,17004,1,17159,1,17161,1,17163,1,17320,1,17322,1]" Type="2" Size="3" Color="1" Angle="0" /></Layout></Component><Component id="1" name="Right"><Layout name="Right_Center_Single" Number="0" Position="[[0.5, 0.75, 0.5, 0.5]]" Uniformity="3"><Entity bbox="[0.5, 0.75, 0.5, 0.5]" real_bbox="[0.5, 0.7625, 0.2062, 0.1937]" mask="[10364,3,10522,6,10679,9,10836,13,10994,16,11151,20,11309,23,11468,24,11628,25,11788,26,11948,27,12108,28,12268,28,12428,29,12588,30,12748,31,12908,31,13068,31,13228,30,13388,29,13548,28,13708,28,13868,27,14028,26,14188,25,14348,24,14509,23,14671,20,14834,16,14996,13,15159,9,15322,6,15484,3]" Type="3" Size="0" Color="4" Angle="1" /></Layout></Component><Component id="2" name="Mesh"><Layout name="Mesh_Layout" Number="6" Position="[[0.08, 0.08, 0.5, 0.08], [0.5, 0.08, 0.92, 0.08], [0.5, 0.08, 0.5, 0.5], [0.92, 0.08, 0.92, 0.5], [0.92, 0.5, 0.92, 0.92], [0.5, 0.5, 0.92, 0.5], [0.5, 0.92, 0.92, 0.92], [0.08, 0.92, 0.5, 0.92], [0.5, 0.5, 0.5, 0.92], [0.08, 0.5, 0.08, 0.92], [0.08, 0.08, 0.08, 0.5], [0.08, 0.5, 0.5, 0.5]]" Uniformity="0"><Entity bbox="[0.5, 0.08, 0.92, 0.08]" real_bbox="[0.3519, -0.0731, 0.3149, 0.3149]" mask="[12653,1,12812,3,12972,3,13132,3,13292,3,13452,3,13612,3,13772,3,13932,3,14092,3,14252,3,14412,3,14572,3,14732,3,14892,3,15052,3,15212,3,15372,3,15532,3,15692,3,15852,3,16012,3,16172,3,16332,3,16492,3,16652,3,16812,3,16972,3,17132,3,17292,3,17452,3,17612,3,17772,3,17932,3,18092,3,18252,3,18412,3,18572,3,18732,3,18892,3,19052,3,19212,3,19372,3,19532,3,19692,3,19852,3,20012,3,20172,3,20332,3,20492,3,20652,3,20812,3,20972,3,21132,3,21292,3,21452,3,21612,3,21772,3,21932,3,22092,3,22252,3,22412,3,22572,3,22732,3,22892,3,23052,3,23212,3,23372,3,23532,3,23693,1]" Type="6" Size="0" Color="0" Angle="0" /><Entity bbox="[0.92, 0.5, 0.92, 0.92]" real_bbox="[1.0668, 0.3519, 0.3149, 0.3149]" mask="[23441,68,23600,70,23761,68]" Type="6" Size="0" Color="0" Angle="0" /><Entity bbox="[0.5, 0.5, 0.92, 0.5]" real_bbox="[0.3519, 0.3519, 0.3149, 0.3149]" mask="[12721,1,12880,3,13040,3,13200,3,13360,3,13520,3,13680,3,13840,3,14000,3,14160,3,14320,3,14480,3,14640,3,14800,3,14960,3,15120,3,15280,3,15440,3,15600,3,15760,3,15920,3,16080,3,16240,3,16400,3,16560,3,16720,3,16880,3,17040,3,17200,3,17360,3,17520,3,17680,3,17840,3,18000,3,18160,3,18320,3,18480,3,18640,3,18800,3,18960,3,19120,3,19280,3,19440,3,19600,3,19760,3,19920,3,20080,3,20240,3,20400,3,20560,3,20720,3,20880,3,21040,3,21200,3,21360,3,21520,3,21680,3,21840,3,22000,3,22160,3,22320,3,22480,3,22640,3,22800,3,22960,3,23120,3,23280,3,23440,3,23600,3,23761,1]" Type="6" Size="0" Color="0" Angle="0" /><Entity bbox="[0.08, 0.08, 0.5, 0.08]" real_bbox="[-0.0753, -0.0753, 0.3193, 0.3193]" mask="[1773,1,1932,3,2092,3,2252,3,2412,3,2572,3,2732,3,2892,3,3052,3,3212,3,3372,3,3532,3,3692,3,3852,3,4012,3,4172,3,4332,3,4492,3,4652,3,4812,3,4972,3,5132,3,5292,3,5452,3,5612,3,5772,3,5932,3,6092,3,6252,3,6412,3,6572,3,6732,3,6892,3,7052,3,7212,3,7372,3,7532,3,7692,3,7852,3,8012,3,8172,3,8332,3,8492,3,8652,3,8812,3,8972,3,9132,3,9292,3,9452,3,9612,3,9772,3,9932,3,10092,3,10252,3,10412,3,10572,3,10732,3,10892,3,11052,3,11212,3,11372,3,11532,3,11692,3,11852,3,12012,3,12172,3,12332,3,12492,3,12652,3,12812,3,12973,1]" Type="6" Size="0" Color="0" Angle="0" /><Entity bbox="[0.08, 0.08, 0.08, 0.5]" real_bbox="[0.2253, -0.0753, 0.3193, 0.3193]" mask="[1773,69,1932,71,2093,69]" Type="6" Size="0" Color="0" Angle="0" /><Entity bbox="[0.5, 0.92, 0.92, 0.92]" real_bbox="[0.3519, 0.7707, 0.3149, 0.3149]" mask="[12788,1,12947,3,13107,3,13267,3,13427,3,13587,3,13747,3,13907,3,14067,3,14227,3,14387,3,14547,3,14707,3,14867,3,15027,3,15187,3,15347,3,15507,3,15667,3,15827,3,15987,3,16147,3,16307,3,16467,3,16627,3,16787,3,16947,3,17107,3,17267,3,17427,3,17587,3,17747,3,17907,3,18067,3,18227,3,18387,3,18547,3,18707,3,18867,3,19027,3,19187,3,19347,3,19507,3,19667,3,19827,3,19987,3,20147,3,20307,3,20467,3,20627,3,20787,3,20947,3,21107,3,21267,3,21427,3,21587,3,21747,3,21907,3,22067,3,22227,3,22387,3,22547,3,22707,3,22867,3,23027,3,23187,3,23347,3,23507,3,23667,3,23828,1]" Type="6" Size="0" Color="0" Angle="0" /><Entity bbox="[0.92, 0.08, 0.92, 0.5]" real_bbox="[1.069, -0.0753, 0.3193, 0.3193]" mask="[23373,69,23532,71,23693,69]" Type="6" Size="0" Color="0" Angle="0" /></Layout></Component></Struct></Panel><Panel><Struct name="Left_Right"><Component id="0" name="Left"><Layout name="Left_Center_Single" Number="0" Position="[[0.5, 0.25, 0.5, 0.5]]" Uniformity="0"><Entity bbox="[0.5, 0.25, 0.5, 0.5]" real_bbox="[0.4779, 0.2279, 0.3104, 0.3104]" mask="[8367,1,8369,1,8526,1,8528,1,8530,155,8686,3,8690,1,8844,1,8850,1,9003,1,9010,1,9162,1,9170,1,9172,149,9322,9,9332,148,9481,9,9491,1,9639,1,9651,1,9653,145,9799,12,9812,145,9958,14,9973,143,10117,14,10132,1,10275,1,10292,1,10294,140,10435,17,10453,1,10593,1,10613,1,10752,1,10773,1,10911,1,10934,1,11070,1,11093,1,11095,134,11230,24,11255,1,11388,1,11414,1,11547,1,11575,1,11706,1,11734,1,11736,129,11866,29,11896,128,12025,30,12056,127,12184,31,12216,1,12342,1,12375,1,12377,124,12502,34,12537,1,12660,1,12696,1,12819,1,12857,1,12978,1,13017,1,13137,1,13176,1,13178,118,13297,40,13338,1,13455,1,13497,1,13499,115,13615,43,13659,114,13774,44,13819,1,13933,1,13935,43,13979,1,14093,1,14095,1,14139,1,14255,1,14257,1,14259,1,14261,38,14300,118,14419,1,14421,1,14423,1,14425,34,14460,121,14582,1,14584,1,14586,1,14620,1,14745,1,14747,1,14749,1,14751,28,14780,1,14909,1,14911,1,14913,1,14915,25,14941,1,15071,1,15073,1,15075,1,15077,1,15079,21,15101,136,15238,1,15240,1,15243,1,15261,1,15399,1,15401,1,15403,1,15405,1,15421,1,15564,1,15566,1,15568,1,15581,1,15583,144,15728,1,15730,1,15732,1,15734,7,15742,150,15893,1,15895,1,15902,1,16054,1,16056,1,16058,1,16060,2,16063,155,16219,1,16221,1,16223]" Type="1" Size="3" Color="1" Angle="0" /></Layout></Component><Component id="1" name="Right"><Layout name="Right_Center_Single" Number="0" Position="[[0.5, 0.75, 0.5, 0.5]]" Uniformity="3"><Entity bbox="[0.5, 0.75, 0.5, 0.5]" real_bbox="[0.5, 0.775, 0.1813, 0.1688]" mask="[10673,1,10832,4,10992,6,11152,8,11312,10,11472,11,11632,13,11792,15,11952,17,12112,19,12272,21,12432,23,12592,24,12752,26,12912,27,13072,26,13232,24,13392,23,13552,21,13712,19,13872,17,14032,15,14192,13,14352,11,14512,10,14672,8,14832,6,14992,4,15153,1]" Type="1" Size="0" Color="5" Angle="1" /></Layout></Component><Component id="2" name="Mesh"><Layout name="Mesh_Layout" Number="6" Position="[[0.08, 0.08, 0.5, 0.08], [0.5, 0.08, 0.92, 0.08], [0.5, 0.08, 0.5, 0.5], [0.92, 0.08, 0.92, 0.5], [0.92, 0.5, 0.92, 0.92], [0.5, 0.5, 0.92, 0.5], [0.5, 0.92, 0.92, 0.92], [0.08, 0.92, 0.5, 0.92], [0.5, 0.5, 0.5, 0.92], [0.08, 0.5, 0.08, 0.92], [0.08, 0.08, 0.08, 0.5], [0.08, 0.5, 0.5, 0.5]]" Uniformity="0"><Entity bbox="[0.5, 0.08, 0.92, 0.08]" real_bbox="[0.3519, -0.0731, 0.3149, 0.3149]" mask="[12653,1,12812,3,12972,3,13132,3,13292,3,13452,3,13612,3,13772,3,13932,3,14092,3,14252,3,14412,3,14572,3,14732,3,14892,3,15052,3,15212,3,15372,3,15532,3,15692,3,15852,3,16012,3,16172,3,16332,3,16492,3,16652,3,16812,3,16972,3,17132,3,17292,3,17452,3,17612,3,17772,3,17932,3,18092,3,18252,3,18412,3,18572,3,18732,3,18892,3,19052,3,19212,3,19372,3,19532,3,19692,3,19852,3,20012,3,20172,3,20332,3,20492,3,20652,3,20812,3,20972,3,21132,3,21292,3,21452,3,21612,3,21772,3,21932,3,22092,3,22252,3,22412,3,22572,3,22732,3,22892,3,23052,3,23212,3,23372,3,23532,3,23693,1]" Type="6" Size="0" Color="0" Angle="0" /><Entity bbox="[0.92, 0.5, 0.92, 0.92]" real_bbox="[1.0668, 0.3519, 0.3149, 0.3149]" mask="[23441,68,23600,70,23761,68]" Type="6" Size="0" Color="0" Angle="0" /><Entity bbox="[0.5, 0.5, 0.92, 0.5]" real_bbox="[0.3519, 0.3519, 0.3149, 0.3149]" mask="[12721,1,12880,3,13040,3,13200,3,13360,3,13520,3,13680,3,13840,3,14000,3,14160,3,14320,3,14480,3,14640,3,14800,3,14960,3,15120,3,15280,3,15440,3,15600,3,15760,3,15920,3,16080,3,16240,3,16400,3,16560,3,16720,3,16880,3,17040,3,17200,3,17360,3,17520,3,17680,3,17840,3,18000,3,18160,3,18320,3,18480,3,18640,3,18800,3,18960,3,19120,3,19280,3,19440,3,19600,3,19760,3,19920,3,20080,3,20240,3,20400,3,20560,3,20720,3,20880,3,21040,3,21200,3,21360,3,21520,3,21680,3,21840,3,22000,3,22160,3,22320,3,22480,3,22640,3,22800,3,22960,3,23120,3,23280,3,23440,3,23600,3,23761,1]" Type="6" Size="0" Color="0" Angle="0" /><Entity bbox="[0.08, 0.08, 0.5, 0.08]" real_bbox="[-0.0753, -0.0753, 0.3193, 0.3193]" mask="[1773,1,1932,3,2092,3,2252,3,2412,3,2572,3,2732,3,2892,3,3052,3,3212,3,3372,3,3532,3,3692,3,3852,3,4012,3,4172,3,4332,3,4492,3,4652,3,4812,3,4972,3,5132,3,5292,3,5452,3,5612,3,5772,3,5932,3,6092,3,6252,3,6412,3,6572,3,6732,3,6892,3,7052,3,7212,3,7372,3,7532,3,7692,3,7852,3,8012,3,8172,3,8332,3,8492,3,8652,3,8812,3,8972,3,9132,3,9292,3,9452,3,9612,3,9772,3,9932,3,10092,3,10252,3,10412,3,10572,3,10732,3,10892,3,11052,3,11212,3,11372,3,11532,3,11692,3,11852,3,12012,3,12172,3,12332,3,12492,3,12652,3,12812,3,12973,1]" Type="6" Size="0" Color="0" Angle="0" /><Entity bbox="[0.08, 0.08, 0.08, 0.5]" real_bbox="[0.2253, -0.0753, 0.3193, 0.3193]" mask="[1773,69,1932,71,2093,69]" Type="6" Size="0" Color="0" Angle="0" /><Entity bbox="[0.5, 0.92, 0.92, 0.92]" real_bbox="[0.3519, 0.7707, 0.3149, 0.3149]" mask="[12788,1,12947,3,13107,3,13267,3,13427,3,13587,3,13747,3,13907,3,14067,3,14227,3,14387,3,14547,3,14707,3,14867,3,15027,3,15187,3,15347,3,15507,3,15667,3,15827,3,15987,3,16147,3,16307,3,16467,3,16627,3,16787,3,16947,3,17107,3,17267,3,17427,3,17587,3,17747,3,17907,3,18067,3,18227,3,18387,3,18547,3,18707,3,18867,3,19027,3,19187,3,19347,3,19507,3,19667,3,19827,3,19987,3,20147,3,20307,3,20467,3,20627,3,20787,3,20947,3,21107,3,21267,3,21427,3,21587,3,21747,3,21907,3,22067,3,22227,3,22387,3,22547,3,22707,3,22867,3,23027,3,23187,3,23347,3,23507,3,23667,3,23828,1]" Type="6" Size="0" Color="0" Angle="0" /><Entity bbox="[0.92, 0.08, 0.92, 0.5]" real_bbox="[1.069, -0.0753, 0.3193, 0.3193]" mask="[23373,69,23532,71,23693,69]" Type="6" Size="0" Color="0" Angle="0" /></Layout></Component></Struct></Panel><Panel><Struct name="Left_Right"><Component id="0" name="Left"><Layout name="Left_Center_Single" Number="0" Position="[[0.5, 0.25, 0.5, 0.5]]" Uniformity="0"><Entity bbox="[0.5, 0.25, 0.5, 0.5]" real_bbox="[0.5, 0.25, 0.3687, 0.3687]" mask="[8036,1,8039,1,8041,1,8043,1,8046,1,8194,1,8196,1,8199,1,8201,1,8203,1,8206,1,8208,1,8351,1,8353,1,8355,1,8367,1,8369,1,8371,1,8508,1,8510,1,8512,19,8532,1,8534,1,8667,1,8669,25,8695,1,8824,1,8826,1,8856,1,8858,1,8983,1,8985,1,9017,1,9019,1,9142,1,9180,1,9301,1,9341,1,9460,1,9502,1,9619,1,9663,1,9778,1,9824,1,9937,1,9985,1,10096,1,10146,1,10257,1,10305,1,10416,1,10466,1,10575,1,10627,1,10734,1,10736,51,10788,1,10894,1,10948,1,11054,1,11108,1,11213,1,11215,53,11269,1,11373,1,11429,1,11533,1,11589,1,11692,1,11750,1,11852,1,11854,55,11910,1,12011,1,12013,57,12071,1,12172,1,12230,1,12332,1,12390,1,12491,1,12493,57,12551,1,12651,1,12653,57,12711,1,12812,1,12870,1,12971,1,12973,57,13031,1,13131,1,13133,57,13191,1,13292,1,13350,1,13452,1,13510,1,13611,1,13613,57,13671,1,13772,1,13774,55,13830,1,13932,1,13990,1,14093,1,14149,1,14253,1,14309,1,14413,1,14415,53,14469,1,14574,1,14628,1,14734,1,14788,1,14894,1,14896,51,14948,1,15055,1,15107,1,15216,1,15266,1,15377,1,15425,1,15536,1,15586,1,15697,1,15745,1,15858,1,15904,1,16019,1,16063,1,16180,1,16222,1,16341,1,16381,1,16502,1,16540,1,16663,1,16665,1,16697,1,16699,1,16824,1,16826,1,16856,1,16858,1,16987,1,16989,25,17015,1,17148,1,17150,1,17152,19,17172,1,17174,1,17311,1,17313,1,17315,1,17327,1,17329,1,17331,1,17474,1,17476,1,17479,1,17481,1,17483,1,17486,1,17488,1,17636,1,17639,1,17641,1,17643,1,17646,1]" Type="5" Size="3" Color="1" Angle="0" /></Layout></Component><Component id="1" name="Right"><Layout name="Right_Center_Single" Number="0" Position="[[0.5, 0.75, 0.5, 0.5]]" Uniformity="3"><Entity bbox="[0.5, 0.75, 0.5, 0.5]" real_bbox="[0.5, 0.75, 0.1813, 0.2187]" mask="[10672,19,10832,19,10991,21,11150,23,11310,23,11469,25,11628,27,11788,27,11947,29,12107,29,12266,31,12425,33,12585,33,12744,35,12904,35,13064,35,13225,33,13385,33,13546,31,13707,29,13867,29,14028,27,14188,27,14349,25,14510,23,14670,23,14831,21,14992,19,15152,19]" Type="4" Size="0" Color="6" Angle="1" /></Layout></Component><Component id="2" name="Mesh"><Layout name="Mesh_Layout" Number="6" Position="[[0.08, 0.08, 0.5, 0.08], [0.5, 0.08, 0.92, 0.08], [0.5, 0.08, 0.5, 0.5], [0.92, 0.08, 0.92, 0.5], [0.92, 0.5, 0.92, 0.92], [0.5, 0.5, 0.92, 0.5], [0.5, 0.92, 0.92, 0.92], [0.08, 0.92, 0.5, 0.92], [0.5, 0.5, 0.5, 0.92], [0.08, 0.5, 0.08, 0.92], [0.08, 0.08, 0.08, 0.5], [0.08, 0.5, 0.5, 0.5]]" Uniformity="0"><Entity bbox="[0.5, 0.08, 0.92, 0.08]" real_bbox="[0.3519, -0.0731, 0.3149, 0.3149]" mask="[12653,1,12812,3,12972,3,13132,3,13292,3,13452,3,13612,3,13772,3,13932,3,14092,3,14252,3,14412,3,14572,3,14732,3,14892,3,15052,3,15212,3,15372,3,15532,3,15692,3,15852,3,16012,3,16172,3,16332,3,16492,3,16652,3,16812,3,16972,3,17132,3,17292,3,17452,3,17612,3,17772,3,17932,3,18092,3,18252,3,18412,3,18572,3,18732,3,18892,3,19052,3,19212,3,19372,3,19532,3,19692,3,19852,3,20012,3,20172,3,20332,3,20492,3,20652,3,20812,3,20972,3,21132,3,21292,3,21452,3,21612,3,21772,3,21932,3,22092,3,22252,3,22412,3,22572,3,22732,3,22892,3,23052,3,23212,3,23372,3,23532,3,23693,1]" Type="6" Size="0" Color="0" Angle="0" /><Entity bbox="[0.92, 0.5, 0.92, 0.92]" real_bbox="[1.0668, 0.3519, 0.3149, 0.3149]" mask="[23441,68,23600,70,23761,68]" Type="6" Size="0" Color="0" Angle="0" /><Entity bbox="[0.5, 0.5, 0.92, 0.5]" real_bbox="[0.3519, 0.3519, 0.3149, 0.3149]" mask="[12721,1,12880,3,13040,3,13200,3,13360,3,13520,3,13680,3,13840,3,14000,3,14160,3,14320,3,14480,3,14640,3,14800,3,14960,3,15120,3,15280,3,15440,3,15600,3,15760,3,15920,3,16080,3,16240,3,16400,3,16560,3,16720,3,16880,3,17040,3,17200,3,17360,3,17520,3,17680,3,17840,3,18000,3,18160,3,18320,3,18480,3,18640,3,18800,3,18960,3,19120,3,19280,3,19440,3,19600,3,19760,3,19920,3,20080,3,20240,3,20400,3,20560,3,20720,3,20880,3,21040,3,21200,3,21360,3,21520,3,21680,3,21840,3,22000,3,22160,3,22320,3,22480,3,22640,3,22800,3,22960,3,23120,3,23280,3,23440,3,23600,3,23761,1]" Type="6" Size="0" Color="0" Angle="0" /><Entity bbox="[0.08, 0.08, 0.5, 0.08]" real_bbox="[-0.0753, -0.0753, 0.3193, 0.3193]" mask="[1773,1,1932,3,2092,3,2252,3,2412,3,2572,3,2732,3,2892,3,3052,3,3212,3,3372,3,3532,3,3692,3,3852,3,4012,3,4172,3,4332,3,4492,3,4652,3,4812,3,4972,3,5132,3,5292,3,5452,3,5612,3,5772,3,5932,3,6092,3,6252,3,6412,3,6572,3,6732,3,6892,3,7052,3,7212,3,7372,3,7532,3,7692,3,7852,3,8012,3,8172,3,8332,3,8492,3,8652,3,8812,3,8972,3,9132,3,9292,3,9452,3,9612,3,9772,3,9932,3,10092,3,10252,3,10412,3,10572,3,10732,3,10892,3,11052,3,11212,3,11372,3,11532,3,11692,3,11852,3,12012,3,12172,3,12332,3,12492,3,12652,3,12812,3,12973,1]" Type="6" Size="0" Color="0" Angle="0" /><Entity bbox="[0.08, 0.08, 0.08, 0.5]" real_bbox="[0.2253, -0.0753, 0.3193, 0.3193]" mask="[1773,69,1932,71,2093,69]" Type="6" Size="0" Color="0" Angle="0" /><Entity bbox="[0.5, 0.92, 0.92, 0.92]" real_bbox="[0.3519, 0.7707, 0.3149, 0.3149]" mask="[12788,1,12947,3,13107,3,13267,3,13427,3,13587,3,13747,3,13907,3,14067,3,14227,3,14387,3,14547,3,14707,3,14867,3,15027,3,15187,3,15347,3,15507,3,15667,3,15827,3,15987,3,16147,3,16307,3,16467,3,16627,3,16787,3,16947,3,17107,3,17267,3,17427,3,17587,3,17747,3,17907,3,18067,3,18227,3,18387,3,18547,3,18707,3,18867,3,19027,3,19187,3,19347,3,19507,3,19667,3,19827,3,19987,3,20147,3,20307,3,20467,3,20627,3,20787,3,20947,3,21107,3,21267,3,21427,3,21587,3,21747,3,21907,3,22067,3,22227,3,22387,3,22547,3,22707,3,22867,3,23027,3,23187,3,23347,3,23507,3,23667,3,23828,1]" Type="6" Size="0" Color="0" Angle="0" /><Entity bbox="[0.92, 0.08, 0.92, 0.5]" real_bbox="[1.069, -0.0753, 0.3193, 0.3193]" mask="[23373,69,23532,71,23693,69]" Type="6" Size="0" Color="0" Angle="0" /></Layout></Component></Struct></Panel><Panel><Struct name="Left_Right"><Component id="0" name="Left"><Layout name="Left_Center_Single" Number="0" Position="[[0.5, 0.25, 0.5, 0.5]]" Uniformity="0"><Entity bbox="[0.5, 0.25, 0.5, 0.5]" real_bbox="[0.45, 0.25, 0.3188, 0.3562]" mask="[7561,1,7720,3,7880,3,8039,5,8198,7,8358,7,8517,9,8677,9,8836,11,8996,11,9155,13,9315,13,9474,15,9633,17,9793,17,9952,19,10112,19,10271,21,10431,21,10590,23,10749,25,10909,25,11068,27,11228,27,11387,29,11547,29,11706,31,11866,31,12025,33,12184,35,12344,35,12503,37,12663,37,12822,39,12982,39,13141,41,13300,43,13460,43,13619,45,13779,45,13938,47,14098,47,14257,49,14417,49,14576,51,14735,53,14895,53,15054,55,15214,55,15373,57,15534,55]" Type="1" Size="4" Color="4" Angle="3" /></Layout></Component><Component id="1" name="Right"><Layout name="Right_Center_Single" Number="0" Position="[[0.5, 0.75, 0.5, 0.5]]" Uniformity="3"><Entity bbox="[0.5, 0.75, 0.5, 0.5]" real_bbox="[0.5, 0.7938, 0.3188, 0.2813]" mask="[8907,1,9066,4,9226,6,9386,7,9546,9,9706,11,9866,13,10026,14,10186,16,10346,18,10506,20,10666,21,10826,23,10986,25,11146,27,11306,28,11466,30,11626,32,11786,34,11946,35,12106,37,12266,39,12426,41,12586,42,12746,44,12906,45,13066,44,13226,42,13386,41,13546,39,13706,37,13866,35,14026,34,14186,32,14346,30,14506,28,14666,27,14826,25,14986,23,15146,21,15306,20,15466,18,15626,16,15786,14,15946,13,16106,11,16266,9,16426,7,16586,6,16746,4,16907,1]" Type="1" Size="3" Color="6" Angle="1" /></Layout></Component><Component id="2" name="Mesh"><Layout name="Mesh_Layout" Number="2" Position="[[0.08, 0.08, 0.5, 0.08], [0.5, 0.08, 0.92, 0.08], [0.5, 0.08, 0.5, 0.5], [0.92, 0.08, 0.92, 0.5], [0.92, 0.5, 0.92, 0.92], [0.5, 0.5, 0.92, 0.5], [0.5, 0.92, 0.92, 0.92], [0.08, 0.92, 0.5, 0.92], [0.5, 0.5, 0.5, 0.92], [0.08, 0.5, 0.08, 0.92], [0.08, 0.08, 0.08, 0.5], [0.08, 0.5, 0.5, 0.5]]" Uniformity="0"><Entity bbox="[0.5, 0.08, 0.92, 0.08]" real_bbox="[0.3519, -0.0731, 0.3149, 0.3149]" mask="[12653,1,12812,3,12972,3,13132,3,13292,3,13452,3,13612,3,13772,3,13932,3,14092,3,14252,3,14412,3,14572,3,14732,3,14892,3,15052,3,15212,3,15372,3,15532,3,15692,3,15852,3,16012,3,16172,3,16332,3,16492,3,16652,3,16812,3,16972,3,17132,3,17292,3,17452,3,17612,3,17772,3,17932,3,18092,3,18252,3,18412,3,18572,3,18732,3,18892,3,19052,3,19212,3,19372,3,19532,3,19692,3,19852,3,20012,3,20172,3,20332,3,20492,3,20652,3,20812,3,20972,3,21132,3,21292,3,21452,3,21612,3,21772,3,21932,3,22092,3,22252,3,22412,3,22572,3,22732,3,22892,3,23052,3,23212,3,23372,3,23532,3,23693,1]" Type="6" Size="0" Color="0" Angle="0" /><Entity bbox="[0.08, 0.08, 0.08, 0.5]" real_bbox="[0.2253, -0.0753, 0.3193, 0.3193]" mask="[1773,69,1932,71,2093,69]" Type="6" Size="0" Color="0" Angle="0" /><Entity bbox="[0.08, 0.5, 0.5, 0.5]" real_bbox="[-0.0753, 0.3497, 0.3193, 0.3193]" mask="[1841,1,2000,3,2160,3,2320,3,2480,3,2640,3,2800,3,2960,3,3120,3,3280,3,3440,3,3600,3,3760,3,3920,3,4080,3,4240,3,4400,3,4560,3,4720,3,4880,3,5040,3,5200,3,5360,3,5520,3,5680,3,5840,3,6000,3,6160,3,6320,3,6480,3,6640,3,6800,3,6960,3,7120,3,7280,3,7440,3,7600,3,7760,3,7920,3,8080,3,8240,3,8400,3,8560,3,8720,3,8880,3,9040,3,9200,3,9360,3,9520,3,9680,3,9840,3,10000,3,10160,3,10320,3,10480,3,10640,3,10800,3,10960,3,11120,3,11280,3,11440,3,11600,3,11760,3,11920,3,12080,3,12240,3,12400,3,12560,3,12720,3,12880,3,13041,1]" Type="6" Size="0" Color="0" Angle="0" /></Layout></Component></Struct></Panel><Panel><Struct name="Left_Right"><Component id="0" name="Left"><Layout name="Left_Center_Single" Number="0" Position="[[0.5, 0.25, 0.5, 0.5]]" Uniformity="0"><Entity bbox="[0.5, 0.25, 0.5, 0.5]" real_bbox="[0.5, 0.25, 0.4188, 0.4188]" mask="[7555,13,7712,20,7869,25,8027,29,8184,35,8343,37,8502,39,8660,43,8819,45,8978,47,9137,49,9296,51,9455,53,9615,53,9774,55,9933,57,10092,59,10252,59,10412,59,10571,61,10731,61,10890,63,11050,63,11210,63,11369,65,11529,65,11689,65,11848,67,12008,67,12168,67,12328,67,12488,67,12648,67,12808,67,12968,67,13128,67,13288,67,13448,67,13608,67,13768,67,13929,65,14089,65,14249,65,14409,65,14570,63,14730,63,14891,61,15051,61,15212,59,15372,59,15532,59,15693,57,15854,55,16015,53,16175,53,16336,51,16497,49,16658,47,16819,45,16980,43,17142,39,17303,37,17464,35,17627,29,17789,25,17952,20,18115,13]" Type="5" Size="4" Color="4" Angle="3" /></Layout></Component><Component id="1" name="Right"><Layout name="Right_Center_Single" Number="0" Position="[[0.5, 0.75, 0.5, 0.5]]" Uniformity="3"><Entity bbox="[0.5, 0.75, 0.5, 0.5]" real_bbox="[0.5, 0.75, 0.3188, 0.3687]" mask="[8906,31,9066,31,9225,33,9384,35,9544,35,9703,37,9863,37,10022,39,10181,41,10341,41,10500,43,10660,43,10819,45,10979,45,11138,47,11297,49,11457,49,11616,51,11776,51,11935,53,12094,55,12254,55,12413,57,12573,57,12732,59,12892,59,13052,59,13213,57,13373,57,13534,55,13694,55,13855,53,14016,51,14176,51,14337,49,14497,49,14658,47,14819,45,14979,45,15140,43,15300,43,15461,41,15621,41,15782,39,15943,37,16103,37,16264,35,16424,35,16585,33,16746,31,16906,31]" Type="4" Size="3" Color="7" Angle="1" /></Layout></Component><Component id="2" name="Mesh"><Layout name="Mesh_Layout" Number="2" Position="[[0.08, 0.08, 0.5, 0.08], [0.5, 0.08, 0.92, 0.08], [0.5, 0.08, 0.5, 0.5], [0.92, 0.08, 0.92, 0.5], [0.92, 0.5, 0.92, 0.92], [0.5, 0.5, 0.92, 0.5], [0.5, 0.92, 0.92, 0.92], [0.08, 0.92, 0.5, 0.92], [0.5, 0.5, 0.5, 0.92], [0.08, 0.5, 0.08, 0.92], [0.08, 0.08, 0.08, 0.5], [0.08, 0.5, 0.5, 0.5]]" Uniformity="0"><Entity bbox="[0.5, 0.08, 0.92, 0.08]" real_bbox="[0.3519, -0.0731, 0.3149, 0.3149]" mask="[12653,1,12812,3,12972,3,13132,3,13292,3,13452,3,13612,3,13772,3,13932,3,14092,3,14252,3,14412,3,14572,3,14732,3,14892,3,15052,3,15212,3,15372,3,15532,3,15692,3,15852,3,16012,3,16172,3,16332,3,16492,3,16652,3,16812,3,16972,3,17132,3,17292,3,17452,3,17612,3,17772,3,17932,3,18092,3,18252,3,18412,3,18572,3,18732,3,18892,3,19052,3,19212,3,19372,3,19532,3,19692,3,19852,3,20012,3,20172,3,20332,3,20492,3,20652,3,20812,3,20972,3,21132,3,21292,3,21452,3,21612,3,21772,3,21932,3,22092,3,22252,3,22412,3,22572,3,22732,3,22892,3,23052,3,23212,3,23372,3,23532,3,23693,1]" Type="6" Size="0" Color="0" Angle="0" /><Entity bbox="[0.08, 0.08, 0.08, 0.5]" real_bbox="[0.2253, -0.0753, 0.3193, 0.3193]" mask="[1773,69,1932,71,2093,69]" Type="6" Size="0" Color="0" Angle="0" /><Entity bbox="[0.08, 0.5, 0.5, 0.5]" real_bbox="[-0.0753, 0.3497, 0.3193, 0.3193]" mask="[1841,1,2000,3,2160,3,2320,3,2480,3,2640,3,2800,3,2960,3,3120,3,3280,3,3440,3,3600,3,3760,3,3920,3,4080,3,4240,3,4400,3,4560,3,4720,3,4880,3,5040,3,5200,3,5360,3,5520,3,5680,3,5840,3,6000,3,6160,3,6320,3,6480,3,6640,3,6800,3,6960,3,7120,3,7280,3,7440,3,7600,3,7760,3,7920,3,8080,3,8240,3,8400,3,8560,3,8720,3,8880,3,9040,3,9200,3,9360,3,9520,3,9680,3,9840,3,10000,3,10160,3,10320,3,10480,3,10640,3,10800,3,10960,3,11120,3,11280,3,11440,3,11600,3,11760,3,11920,3,12080,3,12240,3,12400,3,12560,3,12720,3,12880,3,13041,1]" Type="6" Size="0" Color="0" Angle="0" /></Layout></Component></Struct></Panel><Panel><Struct name="Left_Right"><Component id="0" name="Left"><Layout name="Left_Center_Single" Number="0" Position="[[0.5, 0.25, 0.5, 0.5]]" Uniformity="0"><Entity bbox="[0.5, 0.25, 0.5, 0.5]" real_bbox="[0.5, 0.25, 0.2937, 0.2938]" mask="[9139,45,9298,47,9458,47,9618,47,9778,47,9938,47,10098,47,10258,47,10418,47,10578,47,10738,47,10898,47,11058,47,11218,47,11378,47,11538,47,11698,47,11858,47,12018,47,12178,47,12338,47,12498,47,12658,47,12818,47,12978,47,13138,47,13298,47,13458,47,13618,47,13778,47,13938,47,14098,47,14258,47,14418,47,14578,47,14738,47,14898,47,15058,47,15218,47,15378,47,15538,47,15698,47,15858,47,16018,47,16178,47,16338,47,16499,45]" Type="2" Size="4" Color="4" Angle="3" /></Layout></Component><Component id="1" name="Right"><Layout name="Right_Center_Single" Number="0" Position="[[0.5, 0.75, 0.5, 0.5]]" Uniformity="3"><Entity bbox="[0.5, 0.75, 0.5, 0.5]" real_bbox="[0.5, 0.7719, 0.3938, 0.375]" mask="[7969,3,8126,7,8284,9,8441,13,8598,17,8755,21,8912,24,9069,28,9227,31,9384,35,9541,38,9698,42,9856,45,10015,47,10175,48,10335,48,10495,49,10655,50,10815,51,10975,51,11135,52,11295,53,11455,54,11615,54,11775,55,11935,56,12095,57,12255,57,12415,58,12575,59,12735,60,12895,60,13055,60,13215,59,13375,58,13535,57,13695,57,13855,56,14015,55,14175,54,14335,54,14495,53,14655,52,14815,51,14975,51,15135,50,15295,49,15455,48,15615,48,15775,47,15936,45,16098,42,16261,38,16424,35,16587,31,16749,28,16912,24,17075,21,17238,17,17401,13,17564,9,17726,7,17889,3]" Type="3" Size="4" Color="8" Angle="1" /></Layout></Component><Component id="2" name="Mesh"><Layout name="Mesh_Layout" Number="2" Position="[[0.08, 0.08, 0.5, 0.08], [0.5, 0.08, 0.92, 0.08], [0.5, 0.08, 0.5, 0.5], [0.92, 0.08, 0.92, 0.5], [0.92, 0.5, 0.92, 0.92], [0.5, 0.5, 0.92, 0.5], [0.5, 0.92, 0.92, 0.92], [0.08, 0.92, 0.5, 0.92], [0.5, 0.5, 0.5, 0.92], [0.08, 0.5, 0.08, 0.92], [0.08, 0.08, 0.08, 0.5], [0.08, 0.5, 0.5, 0.5]]" Uniformity="0"><Entity bbox="[0.5, 0.08, 0.92, 0.08]" real_bbox="[0.3519, -0.0731, 0.3149, 0.3149]" mask="[12653,1,12812,3,12972,3,13132,3,13292,3,13452,3,13612,3,13772,3,13932,3,14092,3,14252,3,14412,3,14572,3,14732,3,14892,3,15052,3,15212,3,15372,3,15532,3,15692,3,15852,3,16012,3,16172,3,16332,3,16492,3,16652,3,16812,3,16972,3,17132,3,17292,3,17452,3,17612,3,17772,3,17932,3,18092,3,18252,3,18412,3,18572,3,18732,3,18892,3,19052,3,19212,3,19372,3,19532,3,19692,3,19852,3,20012,3,20172,3,20332,3,20492,3,20652,3,20812,3,20972,3,21132,3,21292,3,21452,3,21612,3,21772,3,21932,3,22092,3,22252,3,22412,3,22572,3,22732,3,22892,3,23052,3,23212,3,23372,3,23532,3,23693,1]" Type="6" Size="0" Color="0" Angle="0" /><Entity bbox="[0.08, 0.08, 0.08, 0.5]" real_bbox="[0.2253, -0.0753, 0.3193, 0.3193]" mask="[1773,69,1932,71,2093,69]" Type="6" Size="0" Color="0" Angle="0" /><Entity bbox="[0.08, 0.5, 0.5, 0.5]" real_bbox="[-0.0753, 0.3497, 0.3193, 0.3193]" mask="[1841,1,2000,3,2160,3,2320,3,2480,3,2640,3,2800,3,2960,3,3120,3,3280,3,3440,3,3600,3,3760,3,3920,3,4080,3,4240,3,4400,3,4560,3,4720,3,4880,3,5040,3,5200,3,5360,3,5520,3,5680,3,5840,3,6000,3,6160,3,6320,3,6480,3,6640,3,6800,3,6960,3,7120,3,7280,3,7440,3,7600,3,7760,3,7920,3,8080,3,8240,3,8400,3,8560,3,8720,3,8880,3,9040,3,9200,3,9360,3,9520,3,9680,3,9840,3,10000,3,10160,3,10320,3,10480,3,10640,3,10800,3,10960,3,11120,3,11280,3,11440,3,11600,3,11760,3,11920,3,12080,3,12240,3,12400,3,12560,3,12720,3,12880,3,13041,1]" Type="6" Size="0" Color="0" Angle="0" /></Layout></Component></Struct></Panel><Panel><Struct name="Left_Right"><Component id="0" name="Left"><Layout name="Left_Center_Single" Number="0" Position="[[0.5, 0.25, 0.5, 0.5]]" Uniformity="0"><Entity bbox="[0.5, 0.25, 0.5, 0.5]" real_bbox="[0.5, 0.25, 0.2563, 0.2563]" mask="[9622,39,9781,41,9941,41,10101,41,10261,41,10421,41,10581,41,10741,41,10901,41,11061,41,11221,41,11381,41,11541,41,11701,41,11861,41,12021,41,12181,41,12341,41,12501,41,12661,41,12821,41,12981,41,13141,41,13301,41,13461,41,13621,41,13781,41,13941,41,14101,41,14261,41,14421,41,14581,41,14741,41,14901,41,15061,41,15221,41,15381,41,15541,41,15701,41,15861,41,16022,39]" Type="2" Size="3" Color="4" Angle="3" /></Layout></Component><Component id="1" name="Right"><Layout name="Right_Center_Single" Number="0" Position="[[0.5, 0.75, 0.5, 0.5]]" Uniformity="3"><Entity bbox="[0.5, 0.75, 0.5, 0.5]" real_bbox="[0.5, 0.7688, 0.3437, 0.3312]" mask="[8608,3,8765,7,8922,10,9079,14,9236,18,9393,22,9550,25,9707,29,9864,33,10021,37,10179,39,10338,41,10498,42,10658,43,10818,44,10978,44,11138,45,11298,46,11458,47,11618,47,11778,48,11938,49,12098,50,12258,50,12418,51,12578,52,12738,53,12898,53,13058,53,13218,52,13378,51,13538,50,13698,50,13858,49,14018,48,14178,47,14338,47,14498,46,14658,45,14818,44,14978,44,15138,43,15298,42,15458,41,15619,39,15781,37,15944,33,16107,29,16270,25,16433,22,16596,18,16759,14,16922,10,17085,7,17248,3]" Type="3" Size="3" Color="8" Angle="1" /></Layout></Component><Component id="2" name="Mesh"><Layout name="Mesh_Layout" Number="2" Position="[[0.08, 0.08, 0.5, 0.08], [0.5, 0.08, 0.92, 0.08], [0.5, 0.08, 0.5, 0.5], [0.92, 0.08, 0.92, 0.5], [0.92, 0.5, 0.92, 0.92], [0.5, 0.5, 0.92, 0.5], [0.5, 0.92, 0.92, 0.92], [0.08, 0.92, 0.5, 0.92], [0.5, 0.5, 0.5, 0.92], [0.08, 0.5, 0.08, 0.92], [0.08, 0.08, 0.08, 0.5], [0.08, 0.5, 0.5, 0.5]]" Uniformity="0"><Entity bbox="[0.5, 0.08, 0.92, 0.08]" real_bbox="[0.3519, -0.0731, 0.3149, 0.3149]" mask="[12653,1,12812,3,12972,3,13132,3,13292,3,13452,3,13612,3,13772,3,13932,3,14092,3,14252,3,14412,3,14572,3,14732,3,14892,3,15052,3,15212,3,15372,3,15532,3,15692,3,15852,3,16012,3,16172,3,16332,3,16492,3,16652,3,16812,3,16972,3,17132,3,17292,3,17452,3,17612,3,17772,3,17932,3,18092,3,18252,3,18412,3,18572,3,18732,3,18892,3,19052,3,19212,3,19372,3,19532,3,19692,3,19852,3,20012,3,20172,3,20332,3,20492,3,20652,3,20812,3,20972,3,21132,3,21292,3,21452,3,21612,3,21772,3,21932,3,22092,3,22252,3,22412,3,22572,3,22732,3,22892,3,23052,3,23212,3,23372,3,23532,3,23693,1]" Type="6" Size="0" Color="0" Angle="0" /><Entity bbox="[0.08, 0.08, 0.08, 0.5]" real_bbox="[0.2253, -0.0753, 0.3193, 0.3193]" mask="[1773,69,1932,71,2093,69]" Type="6" Size="0" Color="0" Angle="0" /><Entity bbox="[0.08, 0.5, 0.5, 0.5]" real_bbox="[-0.0753, 0.3497, 0.3193, 0.3193]" mask="[1841,1,2000,3,2160,3,2320,3,2480,3,2640,3,2800,3,2960,3,3120,3,3280,3,3440,3,3600,3,3760,3,3920,3,4080,3,4240,3,4400,3,4560,3,4720,3,4880,3,5040,3,5200,3,5360,3,5520,3,5680,3,5840,3,6000,3,6160,3,6320,3,6480,3,6640,3,6800,3,6960,3,7120,3,7280,3,7440,3,7600,3,7760,3,7920,3,8080,3,8240,3,8400,3,8560,3,8720,3,8880,3,9040,3,9200,3,9360,3,9520,3,9680,3,9840,3,10000,3,10160,3,10320,3,10480,3,10640,3,10800,3,10960,3,11120,3,11280,3,11440,3,11600,3,11760,3,11920,3,12080,3,12240,3,12400,3,12560,3,12720,3,12880,3,13041,1]" Type="6" Size="0" Color="0" Angle="0" /></Layout></Component></Struct></Panel><Panel><Struct name="Left_Right"><Component id="0" name="Left"><Layout name="Left_Center_Single" Number="0" Position="[[0.5, 0.25, 0.5, 0.5]]" Uniformity="0"><Entity bbox="[0.5, 0.25, 0.5, 0.5]" real_bbox="[0.5, 0.25, 0.2563, 0.2563]" mask="[9622,39,9781,41,9941,41,10101,41,10261,41,10421,41,10581,41,10741,41,10901,41,11061,41,11221,41,11381,41,11541,41,11701,41,11861,41,12021,41,12181,41,12341,41,12501,41,12661,41,12821,41,12981,41,13141,41,13301,41,13461,41,13621,41,13781,41,13941,41,14101,41,14261,41,14421,41,14581,41,14741,41,14901,41,15061,41,15221,41,15381,41,15541,41,15701,41,15861,41,16022,39]" Type="2" Size="3" Color="4" Angle="3" /></Layout></Component><Component id="1" name="Right"><Layout name="Right_Center_Single" Number="0" Position="[[0.5, 0.75, 0.5, 0.5]]" Uniformity="3"><Entity bbox="[0.5, 0.75, 0.5, 0.5]" real_bbox="[0.5, 0.7688, 0.3437, 0.3312]" mask="[8608,3,8765,7,8922,10,9079,14,9236,18,9393,22,9550,25,9707,29,9864,33,10021,37,10179,39,10338,41,10498,42,10658,43,10818,44,10978,44,11138,45,11298,46,11458,47,11618,47,11778,48,11938,49,12098,50,12258,50,12418,51,12578,52,12738,53,12898,53,13058,53,13218,52,13378,51,13538,50,13698,50,13858,49,14018,48,14178,47,14338,47,14498,46,14658,45,14818,44,14978,44,15138,43,15298,42,15458,41,15619,39,15781,37,15944,33,16107,29,16270,25,16433,22,16596,18,16759,14,16922,10,17085,7,17248,3]" Type="3" Size="3" Color="8" Angle="1" /></Layout></Component><Component id="2" name="Mesh"><Layout name="Mesh_Layout" Number="2" Position="[[0.08, 0.08, 0.5, 0.08], [0.5, 0.08, 0.92, 0.08], [0.5, 0.08, 0.5, 0.5], [0.92, 0.08, 0.92, 0.5], [0.92, 0.5, 0.92, 0.92], [0.5, 0.5, 0.92, 0.5], [0.5, 0.92, 0.92, 0.92], [0.08, 0.92, 0.5, 0.92], [0.5, 0.5, 0.5, 0.92], [0.08, 0.5, 0.08, 0.92], [0.08, 0.08, 0.08, 0.5], [0.08, 0.5, 0.5, 0.5]]" Uniformity="0"><Entity bbox="[0.08, 0.5, 0.08, 0.92]" real_bbox="[0.2231, 0.3519, 0.3149, 0.3149]" mask="[1841,68,2000,70,2161,68]" Type="6" Size="0" Color="0" Angle="0" /><Entity bbox="[0.5, 0.92, 0.92, 0.92]" real_bbox="[0.3519, 0.7707, 0.3149, 0.3149]" mask="[12788,1,12947,3,13107,3,13267,3,13427,3,13587,3,13747,3,13907,3,14067,3,14227,3,14387,3,14547,3,14707,3,14867,3,15027,3,15187,3,15347,3,15507,3,15667,3,15827,3,15987,3,16147,3,16307,3,16467,3,16627,3,16787,3,16947,3,17107,3,17267,3,17427,3,17587,3,17747,3,17907,3,18067,3,18227,3,18387,3,18547,3,18707,3,18867,3,19027,3,19187,3,19347,3,19507,3,19667,3,19827,3,19987,3,20147,3,20307,3,20467,3,20627,3,20787,3,20947,3,21107,3,21267,3,21427,3,21587,3,21747,3,21907,3,22067,3,22227,3,22387,3,22547,3,22707,3,22867,3,23027,3,23187,3,23347,3,23507,3,23667,3,23828,1]" Type="6" Size="0" Color="0" Angle="0" /><Entity bbox="[0.5, 0.5, 0.5, 0.92]" real_bbox="[0.6481, 0.3519, 0.3149, 0.3149]" mask="[12721,68,12880,70,13041,68]" Type="6" Size="0" Color="0" Angle="0" /></Layout></Component></Struct></Panel><Panel><Struct name="Left_Right"><Component id="0" name="Left"><Layout name="Left_Center_Single" Number="0" Position="[[0.5, 0.25, 0.5, 0.5]]" Uniformity="0"><Entity bbox="[0.5, 0.25, 0.5, 0.5]" real_bbox="[0.5, 0.25, 0.2563, 0.2563]" mask="[9622,39,9781,41,9941,41,10101,41,10261,41,10421,41,10581,41,10741,41,10901,41,11061,41,11221,41,11381,41,11541,41,11701,41,11861,41,12021,41,12181,41,12341,41,12501,41,12661,41,12821,41,12981,41,13141,41,13301,41,13461,41,13621,41,13781,41,13941,41,14101,41,14261,41,14421,41,14581,41,14741,41,14901,41,15061,41,15221,41,15381,41,15541,41,15701,41,15861,41,16022,39]" Type="2" Size="3" Color="4" Angle="3" /></Layout></Component><Component id="1" name="Right"><Layout name="Right_Center_Single" Number="0" Position="[[0.5, 0.75, 0.5, 0.5]]" Uniformity="3"><Entity bbox="[0.5, 0.75, 0.5, 0.5]" real_bbox="[0.5, 0.7719, 0.3938, 0.375]" mask="[7969,3,8126,7,8284,9,8441,13,8598,17,8755,21,8912,24,9069,28,9227,31,9384,35,9541,38,9698,42,9856,45,10015,47,10175,48,10335,48,10495,49,10655,50,10815,51,10975,51,11135,52,11295,53,11455,54,11615,54,11775,55,11935,56,12095,57,12255,57,12415,58,12575,59,12735,60,12895,60,13055,60,13215,59,13375,58,13535,57,13695,57,13855,56,14015,55,14175,54,14335,54,14495,53,14655,52,14815,51,14975,51,15135,50,15295,49,15455,48,15615,48,15775,47,15936,45,16098,42,16261,38,16424,35,16587,31,16749,28,16912,24,17075,21,17238,17,17401,13,17564,9,17726,7,17889,3]" Type="3" Size="4" Color="8" Angle="1" /></Layout></Component><Component id="2" name="Mesh"><Layout name="Mesh_Layout" Number="2" Position="[[0.08, 0.08, 0.5, 0.08], [0.5, 0.08, 0.92, 0.08], [0.5, 0.08, 0.5, 0.5], [0.92, 0.08, 0.92, 0.5], [0.92, 0.5, 0.92, 0.92], [0.5, 0.5, 0.92, 0.5], [0.5, 0.92, 0.92, 0.92], [0.08, 0.92, 0.5, 0.92], [0.5, 0.5, 0.5, 0.92], [0.08, 0.5, 0.08, 0.92], [0.08, 0.08, 0.08, 0.5], [0.08, 0.5, 0.5, 0.5]]" Uniformity="0"><Entity bbox="[0.08, 0.5, 0.08, 0.92]" real_bbox="[0.2231, 0.3519, 0.3149, 0.3149]" mask="[1841,68,2000,70,2161,68]" Type="6" Size="0" Color="0" Angle="0" /><Entity bbox="[0.5, 0.92, 0.92, 0.92]" real_bbox="[0.3519, 0.7707, 0.3149, 0.3149]" mask="[12788,1,12947,3,13107,3,13267,3,13427,3,13587,3,13747,3,13907,3,14067,3,14227,3,14387,3,14547,3,14707,3,14867,3,15027,3,15187,3,15347,3,15507,3,15667,3,15827,3,15987,3,16147,3,16307,3,16467,3,16627,3,16787,3,16947,3,17107,3,17267,3,17427,3,17587,3,17747,3,17907,3,18067,3,18227,3,18387,3,18547,3,18707,3,18867,3,19027,3,19187,3,19347,3,19507,3,19667,3,19827,3,19987,3,20147,3,20307,3,20467,3,20627,3,20787,3,20947,3,21107,3,21267,3,21427,3,21587,3,21747,3,21907,3,22067,3,22227,3,22387,3,22547,3,22707,3,22867,3,23027,3,23187,3,23347,3,23507,3,23667,3,23828,1]" Type="6" Size="0" Color="0" Angle="0" /><Entity bbox="[0.5, 0.5, 0.5, 0.92]" real_bbox="[0.6481, 0.3519, 0.3149, 0.3149]" mask="[12721,68,12880,70,13041,68]" Type="6" Size="0" Color="0" Angle="0" /></Layout></Component></Struct></Panel><Panel><Struct name="Left_Right"><Component id="0" name="Left"><Layout name="Left_Center_Single" Number="0" Position="[[0.5, 0.25, 0.5, 0.5]]" Uniformity="0"><Entity bbox="[0.5, 0.25, 0.5, 0.5]" real_bbox="[0.5, 0.25, 0.2937, 0.2938]" mask="[9139,45,9298,47,9458,47,9618,47,9778,47,9938,47,10098,47,10258,47,10418,47,10578,47,10738,47,10898,47,11058,47,11218,47,11378,47,11538,47,11698,47,11858,47,12018,47,12178,47,12338,47,12498,47,12658,47,12818,47,12978,47,13138,47,13298,47,13458,47,13618,47,13778,47,13938,47,14098,47,14258,47,14418,47,14578,47,14738,47,14898,47,15058,47,15218,47,15378,47,15538,47,15698,47,15858,47,16018,47,16178,47,16338,47,16499,45]" Type="2" Size="4" Color="4" Angle="3" /></Layout></Component><Component id="1" name="Right"><Layout name="Right_Center_Single" Number="0" Position="[[0.5, 0.75, 0.5, 0.5]]" Uniformity="3"><Entity bbox="[0.5, 0.75, 0.5, 0.5]" real_bbox="[0.5, 0.7688, 0.3437, 0.3312]" mask="[8608,3,8765,7,8922,10,9079,14,9236,18,9393,22,9550,25,9707,29,9864,33,10021,37,10179,39,10338,41,10498,42,10658,43,10818,44,10978,44,11138,45,11298,46,11458,47,11618,47,11778,48,11938,49,12098,50,12258,50,12418,51,12578,52,12738,53,12898,53,13058,53,13218,52,13378,51,13538,50,13698,50,13858,49,14018,48,14178,47,14338,47,14498,46,14658,45,14818,44,14978,44,15138,43,15298,42,15458,41,15619,39,15781,37,15944,33,16107,29,16270,25,16433,22,16596,18,16759,14,16922,10,17085,7,17248,3]" Type="3" Size="3" Color="8" Angle="1" /></Layout></Component><Component id="2" name="Mesh"><Layout name="Mesh_Layout" Number="2" Position="[[0.08, 0.08, 0.5, 0.08], [0.5, 0.08, 0.92, 0.08], [0.5, 0.08, 0.5, 0.5], [0.92, 0.08, 0.92, 0.5], [0.92, 0.5, 0.92, 0.92], [0.5, 0.5, 0.92, 0.5], [0.5, 0.92, 0.92, 0.92], [0.08, 0.92, 0.5, 0.92], [0.5, 0.5, 0.5, 0.92], [0.08, 0.5, 0.08, 0.92], [0.08, 0.08, 0.08, 0.5], [0.08, 0.5, 0.5, 0.5]]" Uniformity="0"><Entity bbox="[0.08, 0.5, 0.08, 0.92]" real_bbox="[0.2231, 0.3519, 0.3149, 0.3149]" mask="[1841,68,2000,70,2161,68]" Type="6" Size="0" Color="0" Angle="0" /><Entity bbox="[0.5, 0.92, 0.92, 0.92]" real_bbox="[0.3519, 0.7707, 0.3149, 0.3149]" mask="[12788,1,12947,3,13107,3,13267,3,13427,3,13587,3,13747,3,13907,3,14067,3,14227,3,14387,3,14547,3,14707,3,14867,3,15027,3,15187,3,15347,3,15507,3,15667,3,15827,3,15987,3,16147,3,16307,3,16467,3,16627,3,16787,3,16947,3,17107,3,17267,3,17427,3,17587,3,17747,3,17907,3,18067,3,18227,3,18387,3,18547,3,18707,3,18867,3,19027,3,19187,3,19347,3,19507,3,19667,3,19827,3,19987,3,20147,3,20307,3,20467,3,20627,3,20787,3,20947,3,21107,3,21267,3,21427,3,21587,3,21747,3,21907,3,22067,3,22227,3,22387,3,22547,3,22707,3,22867,3,23027,3,23187,3,23347,3,23507,3,23667,3,23828,1]" Type="6" Size="0" Color="0" Angle="0" /><Entity bbox="[0.5, 0.5, 0.5, 0.92]" real_bbox="[0.6481, 0.3519, 0.3149, 0.3149]" mask="[12721,68,12880,70,13041,68]" Type="6" Size="0" Color="0" Angle="0" /></Layout></Component></Struct></Panel><Panel><Struct name="Left_Right"><Component id="0" name="Left"><Layout name="Left_Center_Single" Number="0" Position="[[0.5, 0.25, 0.5, 0.5]]" Uniformity="0"><Entity bbox="[0.5, 0.25, 0.5, 0.5]" real_bbox="[0.5, 0.25, 0.2563, 0.2563]" mask="[9622,39,9781,41,9941,41,10101,41,10261,41,10421,41,10581,41,10741,41,10901,41,11061,41,11221,41,11381,41,11541,41,11701,41,11861,41,12021,41,12181,41,12341,41,12501,41,12661,41,12821,41,12981,41,13141,41,13301,41,13461,41,13621,41,13781,41,13941,41,14101,41,14261,41,14421,41,14581,41,14741,41,14901,41,15061,41,15221,41,15381,41,15541,41,15701,41,15861,41,16022,39]" Type="2" Size="3" Color="4" Angle="3" /></Layout></Component><Component id="1" name="Right"><Layout name="Right_Center_Single" Number="0" Position="[[0.5, 0.75, 0.5, 0.5]]" Uniformity="3"><Entity bbox="[0.5, 0.75, 0.5, 0.5]" real_bbox="[0.5, 0.7719, 0.3938, 0.375]" mask="[7969,3,8126,7,8284,9,8441,13,8598,17,8755,21,8912,24,9069,28,9227,31,9384,35,9541,38,9698,42,9856,45,10015,47,10175,48,10335,48,10495,49,10655,50,10815,51,10975,51,11135,52,11295,53,11455,54,11615,54,11775,55,11935,56,12095,57,12255,57,12415,58,12575,59,12735,60,12895,60,13055,60,13215,59,13375,58,13535,57,13695,57,13855,56,14015,55,14175,54,14335,54,14495,53,14655,52,14815,51,14975,51,15135,50,15295,49,15455,48,15615,48,15775,47,15936,45,16098,42,16261,38,16424,35,16587,31,16749,28,16912,24,17075,21,17238,17,17401,13,17564,9,17726,7,17889,3]" Type="3" Size="4" Color="8" Angle="1" /></Layout></Component><Component id="2" name="Mesh"><Layout name="Mesh_Layout" Number="2" Position="[[0.08, 0.08, 0.5, 0.08], [0.5, 0.08, 0.92, 0.08], [0.5, 0.08, 0.5, 0.5], [0.92, 0.08, 0.92, 0.5], [0.92, 0.5, 0.92, 0.92], [0.5, 0.5, 0.92, 0.5], [0.5, 0.92, 0.92, 0.92], [0.08, 0.92, 0.5, 0.92], [0.5, 0.5, 0.5, 0.92], [0.08, 0.5, 0.08, 0.92], [0.08, 0.08, 0.08, 0.5], [0.08, 0.5, 0.5, 0.5]]" Uniformity="0"><Entity bbox="[0.5, 0.08, 0.92, 0.08]" real_bbox="[0.3519, -0.0731, 0.3149, 0.3149]" mask="[12653,1,12812,3,12972,3,13132,3,13292,3,13452,3,13612,3,13772,3,13932,3,14092,3,14252,3,14412,3,14572,3,14732,3,14892,3,15052,3,15212,3,15372,3,15532,3,15692,3,15852,3,16012,3,16172,3,16332,3,16492,3,16652,3,16812,3,16972,3,17132,3,17292,3,17452,3,17612,3,17772,3,17932,3,18092,3,18252,3,18412,3,18572,3,18732,3,18892,3,19052,3,19212,3,19372,3,19532,3,19692,3,19852,3,20012,3,20172,3,20332,3,20492,3,20652,3,20812,3,20972,3,21132,3,21292,3,21452,3,21612,3,21772,3,21932,3,22092,3,22252,3,22412,3,22572,3,22732,3,22892,3,23052,3,23212,3,23372,3,23532,3,23693,1]" Type="6" Size="0" Color="0" Angle="0" /><Entity bbox="[0.08, 0.08, 0.08, 0.5]" real_bbox="[0.2253, -0.0753, 0.3193, 0.3193]" mask="[1773,69,1932,71,2093,69]" Type="6" Size="0" Color="0" Angle="0" /><Entity bbox="[0.08, 0.5, 0.5, 0.5]" real_bbox="[-0.0753, 0.3497, 0.3193, 0.3193]" mask="[1841,1,2000,3,2160,3,2320,3,2480,3,2640,3,2800,3,2960,3,3120,3,3280,3,3440,3,3600,3,3760,3,3920,3,4080,3,4240,3,4400,3,4560,3,4720,3,4880,3,5040,3,5200,3,5360,3,5520,3,5680,3,5840,3,6000,3,6160,3,6320,3,6480,3,6640,3,6800,3,6960,3,7120,3,7280,3,7440,3,7600,3,7760,3,7920,3,8080,3,8240,3,8400,3,8560,3,8720,3,8880,3,9040,3,9200,3,9360,3,9520,3,9680,3,9840,3,10000,3,10160,3,10320,3,10480,3,10640,3,10800,3,10960,3,11120,3,11280,3,11440,3,11600,3,11760,3,11920,3,12080,3,12240,3,12400,3,12560,3,12720,3,12880,3,13041,1]" Type="6" Size="0" Color="0" Angle="0" /></Layout></Component></Struct></Panel><Panel><Struct name="Left_Right"><Component id="0" name="Left"><Layout name="Left_Center_Single" Number="0" Position="[[0.5, 0.25, 0.5, 0.5]]" Uniformity="0"><Entity bbox="[0.5, 0.25, 0.5, 0.5]" real_bbox="[0.5, 0.25, 0.2937, 0.2938]" mask="[9139,45,9298,47,9458,47,9618,47,9778,47,9938,47,10098,47,10258,47,10418,47,10578,47,10738,47,10898,47,11058,47,11218,47,11378,47,11538,47,11698,47,11858,47,12018,47,12178,47,12338,47,12498,47,12658,47,12818,47,12978,47,13138,47,13298,47,13458,47,13618,47,13778,47,13938,47,14098,47,14258,47,14418,47,14578,47,14738,47,14898,47,15058,47,15218,47,15378,47,15538,47,15698,47,15858,47,16018,47,16178,47,16338,47,16499,45]" Type="2" Size="4" Color="4" Angle="3" /></Layout></Component><Component id="1" name="Right"><Layout name="Right_Center_Single" Number="0" Position="[[0.5, 0.75, 0.5, 0.5]]" Uniformity="3"><Entity bbox="[0.5, 0.75, 0.5, 0.5]" real_bbox="[0.5, 0.7688, 0.3437, 0.3312]" mask="[8608,3,8765,7,8922,10,9079,14,9236,18,9393,22,9550,25,9707,29,9864,33,10021,37,10179,39,10338,41,10498,42,10658,43,10818,44,10978,44,11138,45,11298,46,11458,47,11618,47,11778,48,11938,49,12098,50,12258,50,12418,51,12578,52,12738,53,12898,53,13058,53,13218,52,13378,51,13538,50,13698,50,13858,49,14018,48,14178,47,14338,47,14498,46,14658,45,14818,44,14978,44,15138,43,15298,42,15458,41,15619,39,15781,37,15944,33,16107,29,16270,25,16433,22,16596,18,16759,14,16922,10,17085,7,17248,3]" Type="3" Size="3" Color="8" Angle="1" /></Layout></Component><Component id="2" name="Mesh"><Layout name="Mesh_Layout" Number="2" Position="[[0.08, 0.08, 0.5, 0.08], [0.5, 0.08, 0.92, 0.08], [0.5, 0.08, 0.5, 0.5], [0.92, 0.08, 0.92, 0.5], [0.92, 0.5, 0.92, 0.92], [0.5, 0.5, 0.92, 0.5], [0.5, 0.92, 0.92, 0.92], [0.08, 0.92, 0.5, 0.92], [0.5, 0.5, 0.5, 0.92], [0.08, 0.5, 0.08, 0.92], [0.08, 0.08, 0.08, 0.5], [0.08, 0.5, 0.5, 0.5]]" Uniformity="0"><Entity bbox="[0.5, 0.08, 0.92, 0.08]" real_bbox="[0.3519, -0.0731, 0.3149, 0.3149]" mask="[12653,1,12812,3,12972,3,13132,3,13292,3,13452,3,13612,3,13772,3,13932,3,14092,3,14252,3,14412,3,14572,3,14732,3,14892,3,15052,3,15212,3,15372,3,15532,3,15692,3,15852,3,16012,3,16172,3,16332,3,16492,3,16652,3,16812,3,16972,3,17132,3,17292,3,17452,3,17612,3,17772,3,17932,3,18092,3,18252,3,18412,3,18572,3,18732,3,18892,3,19052,3,19212,3,19372,3,19532,3,19692,3,19852,3,20012,3,20172,3,20332,3,20492,3,20652,3,20812,3,20972,3,21132,3,21292,3,21452,3,21612,3,21772,3,21932,3,22092,3,22252,3,22412,3,22572,3,22732,3,22892,3,23052,3,23212,3,23372,3,23532,3,23693,1]" Type="6" Size="0" Color="0" Angle="0" /><Entity bbox="[0.08, 0.08, 0.08, 0.5]" real_bbox="[0.2253, -0.0753, 0.3193, 0.3193]" mask="[1773,69,1932,71,2093,69]" Type="6" Size="0" Color="0" Angle="0" /><Entity bbox="[0.08, 0.5, 0.5, 0.5]" real_bbox="[-0.0753, 0.3497, 0.3193, 0.3193]" mask="[1841,1,2000,3,2160,3,2320,3,2480,3,2640,3,2800,3,2960,3,3120,3,3280,3,3440,3,3600,3,3760,3,3920,3,4080,3,4240,3,4400,3,4560,3,4720,3,4880,3,5040,3,5200,3,5360,3,5520,3,5680,3,5840,3,6000,3,6160,3,6320,3,6480,3,6640,3,6800,3,6960,3,7120,3,7280,3,7440,3,7600,3,7760,3,7920,3,8080,3,8240,3,8400,3,8560,3,8720,3,8880,3,9040,3,9200,3,9360,3,9520,3,9680,3,9840,3,10000,3,10160,3,10320,3,10480,3,10640,3,10800,3,10960,3,11120,3,11280,3,11440,3,11600,3,11760,3,11920,3,12080,3,12240,3,12400,3,12560,3,12720,3,12880,3,13041,1]" Type="6" Size="0" Color="0" Angle="0" /></Layout></Component></Struct></Panel><Panel><Struct name="Left_Right"><Component id="0" name="Left"><Layout name="Left_Center_Single" Number="0" Position="[[0.5, 0.25, 0.5, 0.5]]" Uniformity="0"><Entity bbox="[0.5, 0.25, 0.5, 0.5]" real_bbox="[0.5, 0.25, 0.2937, 0.2938]" mask="[9139,45,9298,47,9458,47,9618,47,9778,47,9938,47,10098,47,10258,47,10418,47,10578,47,10738,47,10898,47,11058,47,11218,47,11378,47,11538,47,11698,47,11858,47,12018,47,12178,47,12338,47,12498,47,12658,47,12818,47,12978,47,13138,47,13298,47,13458,47,13618,47,13778,47,13938,47,14098,47,14258,47,14418,47,14578,47,14738,47,14898,47,15058,47,15218,47,15378,47,15538,47,15698,47,15858,47,16018,47,16178,47,16338,47,16499,45]" Type="2" Size="4" Color="4" Angle="3" /></Layout></Component><Component id="1" name="Right"><Layout name="Right_Center_Single" Number="0" Position="[[0.5, 0.75, 0.5, 0.5]]" Uniformity="3"><Entity bbox="[0.5, 0.75, 0.5, 0.5]" real_bbox="[0.5, 0.7719, 0.3938, 0.375]" mask="[7969,3,8126,7,8284,9,8441,13,8598,17,8755,21,8912,24,9069,28,9227,31,9384,35,9541,38,9698,42,9856,45,10015,47,10175,48,10335,48,10495,49,10655,50,10815,51,10975,51,11135,52,11295,53,11455,54,11615,54,11775,55,11935,56,12095,57,12255,57,12415,58,12575,59,12735,60,12895,60,13055,60,13215,59,13375,58,13535,57,13695,57,13855,56,14015,55,14175,54,14335,54,14495,53,14655,52,14815,51,14975,51,15135,50,15295,49,15455,48,15615,48,15775,47,15936,45,16098,42,16261,38,16424,35,16587,31,16749,28,16912,24,17075,21,17238,17,17401,13,17564,9,17726,7,17889,3]" Type="3" Size="4" Color="8" Angle="1" /></Layout></Component><Component id="2" name="Mesh"><Layout name="Mesh_Layout" Number="2" Position="[[0.08, 0.08, 0.5, 0.08], [0.5, 0.08, 0.92, 0.08], [0.5, 0.08, 0.5, 0.5], [0.92, 0.08, 0.92, 0.5], [0.92, 0.5, 0.92, 0.92], [0.5, 0.5, 0.92, 0.5], [0.5, 0.92, 0.92, 0.92], [0.08, 0.92, 0.5, 0.92], [0.5, 0.5, 0.5, 0.92], [0.08, 0.5, 0.08, 0.92], [0.08, 0.08, 0.08, 0.5], [0.08, 0.5, 0.5, 0.5]]" Uniformity="0"><Entity bbox="[0.08, 0.5, 0.08, 0.92]" real_bbox="[0.2231, 0.3519, 0.3149, 0.3149]" mask="[1841,68,2000,70,2161,68]" Type="6" Size="0" Color="0" Angle="0" /><Entity bbox="[0.5, 0.92, 0.92, 0.92]" real_bbox="[0.3519, 0.7707, 0.3149, 0.3149]" mask="[12788,1,12947,3,13107,3,13267,3,13427,3,13587,3,13747,3,13907,3,14067,3,14227,3,14387,3,14547,3,14707,3,14867,3,15027,3,15187,3,15347,3,15507,3,15667,3,15827,3,15987,3,16147,3,16307,3,16467,3,16627,3,16787,3,16947,3,17107,3,17267,3,17427,3,17587,3,17747,3,17907,3,18067,3,18227,3,18387,3,18547,3,18707,3,18867,3,19027,3,19187,3,19347,3,19507,3,19667,3,19827,3,19987,3,20147,3,20307,3,20467,3,20627,3,20787,3,20947,3,21107,3,21267,3,21427,3,21587,3,21747,3,21907,3,22067,3,22227,3,22387,3,22547,3,22707,3,22867,3,23027,3,23187,3,23347,3,23507,3,23667,3,23828,1]" Type="6" Size="0" Color="0" Angle="0" /><Entity bbox="[0.5, 0.5, 0.5, 0.92]" real_bbox="[0.6481, 0.3519, 0.3149, 0.3149]" mask="[12721,68,12880,70,13041,68]" Type="6" Size="0" Color="0" Angle="0" /></Layout></Component></Struct></Panel></Panels><Rules><Rule_Group id="0"><Rule name="Constant" attr="Number/Position" /><Rule name="Distribute_Three" attr="Type" /><Rule name="Constant" attr="Size" /><Rule name="Constant" attr="Color" /></Rule_Group><Rule_Group id="1"><Rule name="Constant" attr="Number/Position" /><Rule name="Distribute_Three" attr="Type" /><Rule name="Constant" attr="Size" /><Rule name="Progression" attr="Color" /></Rule_Group><Rule_Group id="2"><Rule name="Constant" attr="Number/Position" /><Rule name="Constant" attr="Type" /><Rule name="Constant" attr="Size" /><Rule name="Constant" attr="Color" /></Rule_Group></Rules><Modified_attributes><Candidate id="0"><Attribute component_id="1" name="Size" /></Candidate><Candidate id="1"><Attribute component_id="0" name="Size" /></Candidate><Candidate id="2"><Attribute component_id="2" name="Position" /><Attribute component_id="0" name="Size" /></Candidate><Candidate id="3"><Attribute component_id="2" name="Position" /><Attribute component_id="0" name="Size" /><Attribute component_id="1" name="Size" /></Candidate><Candidate id="4"><Attribute component_id="2" name="Position" /></Candidate><Candidate id="5"><Attribute component_id="0" name="Size" /><Attribute component_id="1" name="Size" /></Candidate><Candidate id="6" /><Candidate id="7"><Attribute component_id="2" name="Position" /><Attribute component_id="1" name="Size" /></Candidate></Modified_attributes></Data>